Workbook

Sheet Dashboard
A1: Vendor Payment & Expense Dashboard
A4: Select Month: | B4: All
A6: Total Spend (₹) | C6: Total Outstanding (Pending+Overdue) (₹) | E6: Overdue Invoice Count | G6: % Paid
A7: {=SUMPRODUCT((IF($B$4="All",1,Raw_Data!$P$2:$P$104=MATCH($B$4,{"Jan","Feb","Mar","Apr","May","Jun"},0)))*Raw_Data!$H$2:$H$104)} -> 5952969.7 | C7: {=SUMPRODUCT((IF($B$4="All",1,Raw_Data!$P$2:$P$104=MATCH($B$4,{"Jan","Feb","Mar","Apr","May","Jun"},0)))*((Raw_Data!$I$2:$I$104="Pending")+(Raw_Data!$I$2:$I$104="Overdue"))*Raw_Data!$H$2:$H$104)} -> 1607513.2 | E7: {=SUMPRODUCT((IF($B$4="All",1,Raw_Data!$P$2:$P$104=MATCH($B$4,{"Jan","Feb","Mar","Apr","May","Jun"},0)))*(Raw_Data!$I$2:$I$104="Overdue"))} -> 19 | G7: {=SUMPRODUCT((IF($B$4="All",1,Raw_Data!$P$2:$P$104=MATCH($B$4,{"Jan","Feb","Mar","Apr","May","Jun"},0)))*(Raw_Data!$I$2:$I$104="Paid"))/SUMPRODUCT((IF($B$4="All",1,Raw_Data!$P$2:$P$104=MATCH($B$4,{"Jan","Feb","Mar","Apr","May","Jun"},0)))*(ROW(Raw_Data!$H$2:$H$104)>0))} -> 0.69902913
A9: Live Pivot — Category x Payment Status (auto-updates with month filter above)
A10: Category | B10: Paid | C10: Pending | D10: Overdue | E10: Grand Total
A11: =Summary!A62 -> Housekeeping | B11: =Summary!B62 -> 383814.6 | C11: =Summary!C62 -> 107784.8 | D11: =Summary!D62 -> 176514.52 | E11: =Summary!E62 -> 668113.92
A12: =Summary!A63 -> Insurance | B12: =Summary!B63 -> 192487.37 | C12: =Summary!C63 -> 127640.72 | D12: =Summary!D63 -> 69289.95 | E12: =Summary!E63 -> 389418.04
A13: =Summary!A64 -> Landscaping | B13: =Summary!B64 -> 458479.15 | C13: =Summary!C64 -> 90106 | D13: =Summary!D64 -> 11947.51 | E13: =Summary!E64 -> 560532.66
A14: =Summary!A65 -> Maintenance | B14: =Summary!B65 -> 927746 | C14: =Summary!C65 -> 29400.73 | D14: =Summary!D65 -> 202823.68 | E14: =Summary!E65 -> 1159970.4
A15: =Summary!A66 -> Marketing | B15: =Summary!B66 -> 119719.48 | C15: =Summary!C66 -> 128668.63 | D15: =Summary!D66 -> 18233.18 | E15: =Summary!E66 -> 266621.29
A16: =Summary!A67 -> Office Supplies | B16: =Summary!B67 -> 226557.38 | C16: =Summary!C67 -> 0 | D16: =Summary!D67 -> 31378.58 | E16: =Summary!E67 -> 257935.96
A17: =Summary!A68 -> Professional Fees | B17: =Summary!B68 -> 652777.28 | C17: =Summary!C68 -> 158639.52 | D17: =Summary!D68 -> 111661.83 | E17: =Summary!E68 -> 923078.63
A18: =Summary!A69 -> Repairs | B18: =Summary!B69 -> 504788.32 | C18: =Summary!C69 -> 0 | D18: =Summary!D69 -> 61735.58 | E18: =Summary!E69 -> 566523.9
A19: =Summary!A70 -> Security | B19: =Summary!B70 -> 390893.44 | C19: =Summary!C70 -> 53441.39 | D19: =Summary!D70 -> 93918.83 | E19: =Summary!E70 -> 538253.66
A20: =Summary!A71 -> Utilities | B20: =Summary!B71 -> 488193.49 | C20: =Summary!C71 -> 102342.02 | D20: =Summary!D71 -> 31985.69 | E20: =Summary!E71 -> 622521.2
A21: =Summary!A72 -> Grand Total | B21: =Summary!B72 -> 4345456.5 | C21: =Summary!C72 -> 798023.81 | D21: =Summary!D72 -> 809489.35 | E21: =Summary!E72 -> 5952969.7
A23: Both charts and the pivot above now recompute live from the month dropdown (cell B4).
A28: Build steps for you to complete by hand (see project guide): PivotTable from Raw_Data, and Power Query merge of the two raw export files.

Sheet Assumptions
A1: Assumptions & Notes
A3: GST Rate Assumed | B3: 0.18
A4: Large Invoice Threshold (₹) | B4: 70000
A5: Dashboard 'As Of' Date | B5: 2026-06-30

Sheet Vendor_Master
A1: Vendor_Name | B1: Category | C1: Payment_Terms_Days | D1: Contact_Person | E1: Onboarded_Date
A2: Shree Maintenance Services | B2: Maintenance | C2: 30 | D2: Contact 1 | E2: 2024-04-12
A3: Apex Security Solutions | B3: Security | C3: 30 | D3: Contact 2 | E3: 2025-03-11
A4: Clean & Clear Housekeeping | B4: Housekeeping | C4: 15 | D4: Contact 3 | E4: 2024-12-14
A5: GreenScape Landscaping | B5: Landscaping | C5: 30 | D5: Contact 4 | E5: 2024-09-27
A6: Delhi Power Utilities Pvt Ltd | B6: Utilities | C6: 15 | D6: Contact 5 | E6: 2024-04-16
A7: Reliable Repairs Co | B7: Repairs | C7: 30 | D7: Contact 6 | E7: 2024-03-12
A8: Capital Insurance Brokers | B8: Insurance | C8: 45 | D8: Contact 7 | E8: 2024-07-07
A9: BrightWay Office Supplies | B9: Office Supplies | C9: 15 | D9: Contact 8 | E9: 2024-01-21
A10: Nexus Professional Consultants | B10: Professional Fees | C10: 45 | D10: Contact 9 | E10: 2024-04-12
A11: UrbanEdge Marketing | B11: Marketing | C11: 30 | D11: Contact 10 | E11: 2024-05-01
A12: SafeGuard Fire & Safety | B12: Maintenance | C12: 30 | D12: Contact 11 | E12: 2025-04-11
A13: Crystal Water Treatment | B13: Utilities | C13: 15 | D13: Contact 12 | E13: 2024-08-02

Sheet Raw_Data
A1: Invoice_No | B1: Vendor_Name | C1: Property_Unit | D1: Invoice_Date | E1: Due_Date | F1: Amount | G1: GST_Amount | H1: Total_Amount | I1: Payment_Status | J1: Payment_Date | K1: Terms_VLOOKUP | L1: Terms_XLOOKUP | M1: Terms_INDEXMATCH | N1: Large_Invoice_Flag | O1: Category_Lookup | P1: Month_No
A2: INV-1001 | B2: Apex Security Solutions | C2: Tower B | D2: 2026-01-01 | E2: 2026-01-31 | F2: 72514.89 | G2: 13052.68 | H2: 85567.57 | I2: Paid | J2: 2026-01-04 | K2: =VLOOKUP(B2,Vendor_Master!$A:$C,3,FALSE()) -> 30 | L2: =_xlfn.XLOOKUP(B2,Vendor_Master!A:A,Vendor_Master!C:C) -> 30 | M2: =INDEX(Vendor_Master!$C:$C,MATCH(B2,Vendor_Master!$A:$A,0)) -> 30 | N2: =IF(H2>Assumptions!$B$4,"Large","") -> Large | O2: =INDEX(Vendor_Master!$B:$B,MATCH(B2,Vendor_Master!$A:$A,0)) -> Security | P2: =MONTH(D2) -> 1
A3: INV-1002 | B3: SafeGuard Fire & Safety | C3: Tower A | D3: 2026-01-24 | E3: 2026-02-23 | F3: 85619.62 | G3: 15411.53 | H3: 101031.15 | I3: Paid | J3: 2026-01-25 | K3: =VLOOKUP(B3,Vendor_Master!$A:$C,3,FALSE()) -> 30 | L3: =_xlfn.XLOOKUP(B3,Vendor_Master!A:A,Vendor_Master!C:C) -> 30 | M3: =INDEX(Vendor_Master!$C:$C,MATCH(B3,Vendor_Master!$A:$A,0)) -> 30 | N3: =IF(H3>Assumptions!$B$4,"Large","") -> Large | O3: =INDEX(Vendor_Master!$B:$B,MATCH(B3,Vendor_Master!$A:$A,0)) -> Maintenance | P3: =MONTH(D3) -> 1
A4: INV-1003 | B4: Shree Maintenance Services | C4: Tower A | D4: 2026-01-03 | E4: 2026-02-02 | F4: 27021.5 | G4: 4863.87 | H4: 31885.37 | I4: Paid | J4: 2026-02-03 | K4: =VLOOKUP(B4,Vendor_Master!$A:$C,3,FALSE()) -> 30 | L4: =_xlfn.XLOOKUP(B4,Vendor_Master!A:A,Vendor_Master!C:C) -> 30 | M4: =INDEX(Vendor_Master!$C:$C,MATCH(B4,Vendor_Master!$A:$A,0)) -> 30 | N4: =IF(H4>Assumptions!$B$4,"Large","") | O4: =INDEX(Vendor_Master!$B:$B,MATCH(B4,Vendor_Master!$A:$A,0)) -> Maintenance | P4: =MONTH(D4) -> 1
A5: INV-1004 | B5: Capital Insurance Brokers | C5: Commercial Block | D5: 2026-01-08 | E5: 2026-02-22 | F5: 47081.19 | G5: 8474.61 | H5: 55555.8 | I5: Overdue | K5: =VLOOKUP(B5,Vendor_Master!$A:$C,3,FALSE()) -> 45 | L5: =_xlfn.XLOOKUP(B5,Vendor_Master!A:A,Vendor_Master!C:C) -> 45 | M5: =INDEX(Vendor_Master!$C:$C,MATCH(B5,Vendor_Master!$A:$A,0)) -> 45 | N5: =IF(H5>Assumptions!$B$4,"Large","") | O5: =INDEX(Vendor_Master!$B:$B,MATCH(B5,Vendor_Master!$A:$A,0)) -> Insurance | P5: =MONTH(D5) -> 1
A6: INV-1005 | B6: Shree Maintenance Services | C6: Retail Plaza | D6: 2026-01-25 | E6: 2026-02-24 | F6: 78106.27 | G6: 14059.13 | H6: 92165.4 | I6: Paid | J6: 2026-01-31 | K6: =VLOOKUP(B6,Vendor_Master!$A:$C,3,FALSE()) -> 30 | L6: =_xlfn.XLOOKUP(B6,Vendor_Master!A:A,Vendor_Master!C:C) -> 30 | M6: =INDEX(Vendor_Master!$C:$C,MATCH(B6,Vendor_Master!$A:$A,0)) -> 30 | N6: =IF(H6>Assumptions!$B$4,"Large","") -> Large | O6: =INDEX(Vendor_Master!$B:$B,MATCH(B6,Vendor_Master!$A:$A,0)) -> Maintenance | P6: =MONTH(D6) -> 1
A7: INV-1006 | B7: GreenScape Landscaping | C7: Tower A | D7: 2026-01-25 | E7: 2026-02-24 | F7: 37283.73 | G7: 6711.07 | H7: 43994.8 | I7: Paid | J7: 2026-02-13 | K7: =VLOOKUP(B7,Vendor_Master!$A:$C,3,FALSE()) -> 30 | L7: =_xlfn.XLOOKUP(B7,Vendor_Master!A:A,Vendor_Master!C:C) -> 30 | M7: =INDEX(Vendor_Master!$C:$C,MATCH(B7,Vendor_Master!$A:$A,0)) -> 30 | N7: =IF(H7>Assumptions!$B$4,"Large","") | O7: =INDEX(Vendor_Master!$B:$B,MATCH(B7,Vendor_Master!$A:$A,0)) -> Landscaping | P7: =MONTH(D7) -> 1
A8: INV-1007 | B8: Reliable Repairs Co | C8: Tower A | D8: 2026-01-20 | E8: 2026-02-19 | F8: 31013.32 | G8: 5582.4 | H8: 36595.72 | I8: Paid | J8: 2026-02-20 | K8: =VLOOKUP(B8,Vendor_Master!$A:$C,3,FALSE()) -> 30 | L8: =_xlfn.XLOOKUP(B8,Vendor_Master!A:A,Vendor_Master!C:C) -> 30 | M8: =INDEX(Vendor_Master!$C:$C,MATCH(B8,Vendor_Master!$A:$A,0)) -> 30 | N8: =IF(H8>Assumptions!$B$4,"Large","") | O8: =INDEX(Vendor_Master!$B:$B,MATCH(B8,Vendor_Master!$A:$A,0)) -> Repairs | P8: =MONTH(D8) -> 1
A9: INV-1008 | B9: Apex Security Solutions | C9: Commercial Block | D9: 2026-01-13 | E9: 2026-02-12 | F9: 14855.62 | G9: 2674.01 | H9: 17529.63 | I9: Overdue | K9: =VLOOKUP(B9,Vendor_Master!$A:$C,3,FALSE()) -> 30 | L9: =_xlfn.XLOOKUP(B9,Vendor_Master!A:A,Vendor_Master!C:C) -> 30 | M9: =INDEX(Vendor_Master!$C:$C,MATCH(B9,Vendor_Master!$A:$A,0)) -> 30 | N9: =IF(H9>Assumptions!$B$4,"Large","") | O9: =INDEX(Vendor_Master!$B:$B,MATCH(B9,Vendor_Master!$A:$A,0)) -> Security | P9: =MONTH(D9) -> 1
A10: INV-1009 | B10: UrbanEdge Marketing | C10: Tower B | D10: 2026-01-28 | E10: 2026-02-27 | F10: 39462.25 | G10: 7103.2 | H10: 46565.45 | I10: Paid | J10: 2026-01-29 | K10: =VLOOKUP(B10,Vendor_Master!$A:$C,3,FALSE()) -> 30 | L10: =_xlfn.XLOOKUP(B10,Vendor_Master!A:A,Vendor_Master!C:C) -> 30 | M10: =INDEX(Vendor_Master!$C:$C,MATCH(B10,Vendor_Master!$A:$A,0)) -> 30 | N10: =IF(H10>Assumptions!$B$4,"Large","") | O10: =INDEX(Vendor_Master!$B:$B,MATCH(B10,Vendor_Master!$A:$A,0)) -> Marketing | P10: =MONTH(D10) -> 1
A11: INV-1010 | B11: SafeGuard Fire & Safety | C11: Tower A | D11: 2026-01-08 | E11: 2026-02-07 | F11: 75256.95 | G11: 13546.25 | H11: 88803.2 | I11: Overdue | K11: =VLOOKUP(B11,Vendor_Master!$A:$C,3,FALSE()) -> 30 | L11: =_xlfn.XLOOKUP(B11,Vendor_Master!A:A,Vendor_Master!C:C) -> 30 | M11: =INDEX(Vendor_Master!$C:$C,MATCH(B11,Vendor_Master!$A:$A,0)) -> 30 | N11: =IF(H11>Assumptions!$B$4,"Large","") -> Large | O11: =INDEX(Vendor_Master!$B:$B,MATCH(B11,Vendor_Master!$A:$A,0)) -> Maintenance | P11: =MONTH(D11) -> 1
A12: INV-1011 | B12: Apex Security Solutions | C12: Commercial Block | D12: 2026-01-13 | E12: 2026-02-12 | F12: 32183.7 | G12: 5793.07 | H12: 37976.77 | I12: Paid | J12: 2026-02-01 | K12: =VLOOKUP(B12,Vendor_Master!$A:$C,3,FALSE()) -> 30 | L12: =_xlfn.XLOOKUP(B12,Vendor_Master!A:A,Vendor_Master!C:C) -> 30 | M12: =INDEX(Vendor_Master!$C:$C,MATCH(B12,Vendor_Master!$A:$A,0)) -> 30 | N12: =IF(H12>Assumptions!$B$4,"Large","") | O12: =INDEX(Vendor_Master!$B:$B,MATCH(B12,Vendor_Master!$A:$A,0)) -> Security | P12: =MONTH(D12) -> 1
A13: INV-1012 | B13: SafeGuard Fire & Safety | C13: Tower A | D13: 2026-01-23 | E13: 2026-02-22 | F13: 69058.37 | G13: 12430.51 | H13: 81488.88 | I13: Paid | J13: 2026-01-30 | K13: =VLOOKUP(B13,Vendor_Master!$A:$C,3,FALSE()) -> 30 | L13: =_xlfn.XLOOKUP(B13,Vendor_Master!A:A,Vendor_Master!C:C) -> 30 | M13: =INDEX(Vendor_Master!$C:$C,MATCH(B13,Vendor_Master!$A:$A,0)) -> 30 | N13: =IF(H13>Assumptions!$B$4,"Large","") -> Large | O13: =INDEX(Vendor_Master!$B:$B,MATCH(B13,Vendor_Master!$A:$A,0)) -> Maintenance | P13: =MONTH(D13) -> 1
A14: INV-1013 | B14: Nexus Professional Consultants | C14: Retail Plaza | D14: 2026-02-07 | E14: 2026-03-24 | F14: 29298.55 | G14: 5273.74 | H14: 34572.29 | I14: Paid | J14: 2026-03-16 | K14: =VLOOKUP(B14,Vendor_Master!$A:$C,3,FALSE()) -> 45 | L14: =_xlfn.XLOOKUP(B14,Vendor_Master!A:A,Vendor_Master!C:C) -> 45 | M14: =INDEX(Vendor_Master!$C:$C,MATCH(B14,Vendor_Master!$A:$A,0)) -> 45 | N14: =IF(H14>Assumptions!$B$4,"Large","") | O14: =INDEX(Vendor_Master!$B:$B,MATCH(B14,Vendor_Master!$A:$A,0)) -> Professional Fees | P14: =MONTH(D14) -> 2
A15: INV-1014 | B15: Crystal Water Treatment | C15: Commercial Block | D15: 2026-02-01 | E15: 2026-02-16 | F15: 27106.52 | G15: 4879.17 | H15: 31985.69 | I15: Overdue | K15: =VLOOKUP(B15,Vendor_Master!$A:$C,3,FALSE()) -> 15 | L15: =_xlfn.XLOOKUP(B15,Vendor_Master!A:A,Vendor_Master!C:C) -> 15 | M15: =INDEX(Vendor_Master!$C:$C,MATCH(B15,Vendor_Master!$A:$A,0)) -> 15 | N15: =IF(H15>Assumptions!$B$4,"Large","") | O15: =INDEX(Vendor_Master!$B:$B,MATCH(B15,Vendor_Master!$A:$A,0)) -> Utilities | P15: =MONTH(D15) -> 2
A16: INV-1015 | B16: Shree Maintenance Services | C16: Commercial Block | D16: 2026-01-22 | E16: 2026-02-21 | F16: 79496.83 | G16: 14309.43 | H16: 93806.26 | I16: Paid | J16: 2026-01-23 | K16: =VLOOKUP(B16,Vendor_Master!$A:$C,3,FALSE()) -> 30 | L16: =_xlfn.XLOOKUP(B16,Vendor_Master!A:A,Vendor_Master!C:C) -> 30 | M16: =INDEX(Vendor_Master!$C:$C,MATCH(B16,Vendor_Master!$A:$A,0)) -> 30 | N16: =IF(H16>Assumptions!$B$4,"Large","") -> Large | O16: =INDEX(Vendor_Master!$B:$B,MATCH(B16,Vendor_Master!$A:$A,0)) -> Maintenance | P16: =MONTH(D16) -> 1
A17: INV-1016 | B17: GreenScape Landscaping | C17: Commercial Block | D17: 2026-02-02 | E17: 2026-03-04 | F17: 84243.98 | G17: 15163.92 | H17: 99407.9 | I17: Paid | J17: 2026-03-02 | K17: =VLOOKUP(B17,Vendor_Master!$A:$C,3,FALSE()) -> 30 | L17: =_xlfn.XLOOKUP(B17,Vendor_Master!A:A,Vendor_Master!C:C) -> 30 | M17: =INDEX(Vendor_Master!$C:$C,MATCH(B17,Vendor_Master!$A:$A,0)) -> 30 | N17: =IF(H17>Assumptions!$B$4,"Large","") -> Large | O17: =INDEX(Vendor_Master!$B:$B,MATCH(B17,Vendor_Master!$A:$A,0)) -> Landscaping | P17: =MONTH(D17) -> 2
A18: INV-1017 | B18: Capital Insurance Brokers | C18: Commercial Block | D18: 2026-02-04 | E18: 2026-03-21 | F18: 47920.11 | G18: 8625.62 | H18: 56545.73 | I18: Paid | J18: 2026-03-20 | K18: =VLOOKUP(B18,Vendor_Master!$A:$C,3,FALSE()) -> 45 | L18: =_xlfn.XLOOKUP(B18,Vendor_Master!A:A,Vendor_Master!C:C) -> 45 | M18: =INDEX(Vendor_Master!$C:$C,MATCH(B18,Vendor_Master!$A:$A,0)) -> 45 | N18: =IF(H18>Assumptions!$B$4,"Large","") | O18: =INDEX(Vendor_Master!$B:$B,MATCH(B18,Vendor_Master!$A:$A,0)) -> Insurance | P18: =MONTH(D18) -> 2
A19: INV-1018 | B19: Nexus Professional Consultants | C19: Retail Plaza | D19: 2026-02-01 | E19: 2026-03-18 | F19: 30858.52 | G19: 5554.53 | H19: 36413.05 | I19: Overdue | K19: =VLOOKUP(B19,Vendor_Master!$A:$C,3,FALSE()) -> 45 | L19: =_xlfn.XLOOKUP(B19,Vendor_Master!A:A,Vendor_Master!C:C) -> 45 | M19: =INDEX(Vendor_Master!$C:$C,MATCH(B19,Vendor_Master!$A:$A,0)) -> 45 | N19: =IF(H19>Assumptions!$B$4,"Large","") | O19: =INDEX(Vendor_Master!$B:$B,MATCH(B19,Vendor_Master!$A:$A,0)) -> Professional Fees | P19: =MONTH(D19) -> 2
A20: INV-1019 | B20: Reliable Repairs Co | C20: Tower B | D20: 2026-02-05 | E20: 2026-03-07 | F20: 94767.34 | G20: 17058.12 | H20: 111825.46 | I20: Paid | J20: 2026-02-07 | K20: =VLOOKUP(B20,Vendor_Master!$A:$C,3,FALSE()) -> 30 | L20: =_xlfn.XLOOKUP(B20,Vendor_Master!A:A,Vendor_Master!C:C) -> 30 | M20: =INDEX(Vendor_Master!$C:$C,MATCH(B20,Vendor_Master!$A:$A,0)) -> 30 | N20: =IF(H20>Assumptions!$B$4,"Large","") -> Large | O20: =INDEX(Vendor_Master!$B:$B,MATCH(B20,Vendor_Master!$A:$A,0)) -> Repairs | P20: =MONTH(D20) -> 2
A21: INV-1020 | B21: Shree Maintenance Services | C21: Tower B | D21: 2026-02-25 | E21: 2026-03-27 | F21: 17539.47 | G21: 3157.1 | H21: 20696.57 | I21: Overdue | K21: =VLOOKUP(B21,Vendor_Master!$A:$C,3,FALSE()) -> 30 | L21: =_xlfn.XLOOKUP(B21,Vendor_Master!A:A,Vendor_Master!C:C) -> 30 | M21: =INDEX(Vendor_Master!$C:$C,MATCH(B21,Vendor_Master!$A:$A,0)) -> 30 | N21: =IF(H21>Assumptions!$B$4,"Large","") | O21: =INDEX(Vendor_Master!$B:$B,MATCH(B21,Vendor_Master!$A:$A,0)) -> Maintenance | P21: =MONTH(D21) -> 2
A22: INV-1021 | B22: Capital Insurance Brokers | C22: Retail Plaza | D22: 2026-02-17 | E22: 2026-04-03 | F22: 13526.91 | G22: 2434.84 | H22: 15961.75 | I22: Paid | J22: 2026-03-15 | K22: =VLOOKUP(B22,Vendor_Master!$A:$C,3,FALSE()) -> 45 | L22: =_xlfn.XLOOKUP(B22,Vendor_Master!A:A,Vendor_Master!C:C) -> 45 | M22: =INDEX(Vendor_Master!$C:$C,MATCH(B22,Vendor_Master!$A:$A,0)) -> 45 | N22: =IF(H22>Assumptions!$B$4,"Large","") | O22: =INDEX(Vendor_Master!$B:$B,MATCH(B22,Vendor_Master!$A:$A,0)) -> Insurance | P22: =MONTH(D22) -> 2
A23: INV-1022 | B23: Nexus Professional Consultants | C23: Tower A | D23: 2026-02-06 | E23: 2026-03-23 | F23: 92483.82 | G23: 16647.09 | H23: 109130.91 | I23: Paid | J23: 2026-02-10 | K23: =VLOOKUP(B23,Vendor_Master!$A:$C,3,FALSE()) -> 45 | L23: =_xlfn.XLOOKUP(B23,Vendor_Master!A:A,Vendor_Master!C:C) -> 45 | M23: =INDEX(Vendor_Master!$C:$C,MATCH(B23,Vendor_Master!$A:$A,0)) -> 45 | N23: =IF(H23>Assumptions!$B$4,"Large","") -> Large | O23: =INDEX(Vendor_Master!$B:$B,MATCH(B23,Vendor_Master!$A:$A,0)) -> Professional Fees | P23: =MONTH(D23) -> 2
A24: INV-1023 | B24: SafeGuard Fire & Safety | C24: Commercial Block | D24: 2026-02-15 | E24: 2026-03-17 | F24: 73326.37 | G24: 13198.75 | H24: 86525.12 | I24: Paid | J24: 2026-03-11 | K24: =VLOOKUP(B24,Vendor_Master!$A:$C,3,FALSE()) -> 30 | L24: =_xlfn.XLOOKUP(B24,Vendor_Master!A:A,Vendor_Master!C:C) -> 30 | M24: =INDEX(Vendor_Master!$C:$C,MATCH(B24,Vendor_Master!$A:$A,0)) -> 30 | N24: =IF(H24>Assumptions!$B$4,"Large","") -> Large | O24: =INDEX(Vendor_Master!$B:$B,MATCH(B24,Vendor_Master!$A:$A,0)) -> Maintenance | P24: =MONTH(D24) -> 2
A25: INV-1024 | B25: Clean & Clear Housekeeping | C25: Commercial Block | D25: 2026-02-12 | E25: 2026-02-27 | F25: 8282.34 | G25: 1490.82 | H25: 9773.16 | I25: Overdue | K25: =VLOOKUP(B25,Vendor_Master!$A:$C,3,FALSE()) -> 15 | L25: =_xlfn.XLOOKUP(B25,Vendor_Master!A:A,Vendor_Master!C:C) -> 15 | M25: =INDEX(Vendor_Master!$C:$C,MATCH(B25,Vendor_Master!$A:$A,0)) -> 15 | N25: =IF(H25>Assumptions!$B$4,"Large","") | O25: =INDEX(Vendor_Master!$B:$B,MATCH(B25,Vendor_Master!$A:$A,0)) -> Housekeeping | P25: =MONTH(D25) -> 2
A26: INV-1025 | B26: Clean & Clear Housekeeping | C26: Commercial Block | D26: 2026-02-14 | E26: 2026-03-01 | F26: 87398.62 | G26: 15731.75 | H26: 103130.37 | I26: Overdue | K26: =VLOOKUP(B26,Vendor_Master!$A:$C,3,FALSE()) -> 15 | L26: =_xlfn.XLOOKUP(B26,Vendor_Master!A:A,Vendor_Master!C:C) -> 15 | M26: =INDEX(Vendor_Master!$C:$C,MATCH(B26,Vendor_Master!$A:$A,0)) -> 15 | N26: =IF(H26>Assumptions!$B$4,"Large","") -> Large | O26: =INDEX(Vendor_Master!$B:$B,MATCH(B26,Vendor_Master!$A:$A,0)) -> Housekeeping | P26: =MONTH(D26) -> 2
A27: INV-1026 | B27: Nexus Professional Consultants | C27: Commercial Block | D27: 2026-02-17 | E27: 2026-04-03 | F27: 25305.27 | G27: 4554.95 | H27: 29860.22 | I27: Overdue | K27: =VLOOKUP(B27,Vendor_Master!$A:$C,3,FALSE()) -> 45 | L27: =_xlfn.XLOOKUP(B27,Vendor_Master!A:A,Vendor_Master!C:C) -> 45 | M27: =INDEX(Vendor_Master!$C:$C,MATCH(B27,Vendor_Master!$A:$A,0)) -> 45 | N27: =IF(H27>Assumptions!$B$4,"Large","") | O27: =INDEX(Vendor_Master!$B:$B,MATCH(B27,Vendor_Master!$A:$A,0)) -> Professional Fees | P27: =MONTH(D27) -> 2
A28: INV-1027 | B28: Nexus Professional Consultants | C28: Tower A | D28: 2026-02-22 | E28: 2026-04-08 | F28: 88251.77 | G28: 15885.32 | H28: 104137.09 | I28: Paid | J28: 2026-03-22 | K28: =VLOOKUP(B28,Vendor_Master!$A:$C,3,FALSE()) -> 45 | L28: =_xlfn.XLOOKUP(B28,Vendor_Master!A:A,Vendor_Master!C:C) -> 45 | M28: =INDEX(Vendor_Master!$C:$C,MATCH(B28,Vendor_Master!$A:$A,0)) -> 45 | N28: =IF(H28>Assumptions!$B$4,"Large","") -> Large | O28: =INDEX(Vendor_Master!$B:$B,MATCH(B28,Vendor_Master!$A:$A,0)) -> Professional Fees | P28: =MONTH(D28) -> 2
A29: INV-1028 | B29: Apex Security Solutions | C29: Commercial Block | D29: 2026-02-23 | E29: 2026-03-25 | F29: 84448.8 | G29: 15200.78 | H29: 99649.58 | I29: Paid | J29: 2026-03-07 | K29: =VLOOKUP(B29,Vendor_Master!$A:$C,3,FALSE()) -> 30 | L29: =_xlfn.XLOOKUP(B29,Vendor_Master!A:A,Vendor_Master!C:C) -> 30 | M29: =INDEX(Vendor_Master!$C:$C,MATCH(B29,Vendor_Master!$A:$A,0)) -> 30 | N29: =IF(H29>Assumptions!$B$4,"Large","") -> Large | O29: =INDEX(Vendor_Master!$B:$B,MATCH(B29,Vendor_Master!$A:$A,0)) -> Security | P29: =MONTH(D29) -> 2
A30: INV-1029 | B30: UrbanEdge Marketing | C30: Retail Plaza | D30: 2026-02-14 | E30: 2026-03-16 | F30: 15451.85 | G30: 2781.33 | H30: 18233.18 | I30: Overdue | K30: =VLOOKUP(B30,Vendor_Master!$A:$C,3,FALSE()) -> 30 | L30: =_xlfn.XLOOKUP(B30,Vendor_Master!A:A,Vendor_Master!C:C) -> 30 | M30: =INDEX(Vendor_Master!$C:$C,MATCH(B30,Vendor_Master!$A:$A,0)) -> 30 | N30: =IF(H30>Assumptions!$B$4,"Large","") | O30: =INDEX(Vendor_Master!$B:$B,MATCH(B30,Vendor_Master!$A:$A,0)) -> Marketing | P30: =MONTH(D30) -> 2
A31: INV-1030 | B31: Nexus Professional Consultants | C31: Retail Plaza | D31: 2026-03-08 | E31: 2026-04-22 | F31: 18941.16 | G31: 3409.41 | H31: 22350.57 | I31: Overdue | K31: =VLOOKUP(B31,Vendor_Master!$A:$C,3,FALSE()) -> 45 | L31: =_xlfn.XLOOKUP(B31,Vendor_Master!A:A,Vendor_Master!C:C) -> 45 | M31: =INDEX(Vendor_Master!$C:$C,MATCH(B31,Vendor_Master!$A:$A,0)) -> 45 | N31: =IF(H31>Assumptions!$B$4,"Large","") | O31: =INDEX(Vendor_Master!$B:$B,MATCH(B31,Vendor_Master!$A:$A,0)) -> Professional Fees | P31: =MONTH(D31) -> 3
A32: INV-1031 | B32: Clean & Clear Housekeeping | C32: Retail Plaza | D32: 2026-02-20 | E32: 2026-03-07 | F32: 53907.62 | G32: 9703.37 | H32: 63610.99 | I32: Overdue | K32: =VLOOKUP(B32,Vendor_Master!$A:$C,3,FALSE()) -> 15 | L32: =_xlfn.XLOOKUP(B32,Vendor_Master!A:A,Vendor_Master!C:C) -> 15 | M32: =INDEX(Vendor_Master!$C:$C,MATCH(B32,Vendor_Master!$A:$A,0)) -> 15 | N32: =IF(H32>Assumptions!$B$4,"Large","") | O32: =INDEX(Vendor_Master!$B:$B,MATCH(B32,Vendor_Master!$A:$A,0)) -> Housekeeping | P32: =MONTH(D32) -> 2
A33: INV-1032 | B33: Nexus Professional Consultants | C33: Tower B | D33: 2026-03-08 | E33: 2026-04-22 | F33: 71504 | G33: 12870.72 | H33: 84374.72 | I33: Paid | J33: 2026-03-30 | K33: =VLOOKUP(B33,Vendor_Master!$A:$C,3,FALSE()) -> 45 | L33: =_xlfn.XLOOKUP(B33,Vendor_Master!A:A,Vendor_Master!C:C) -> 45 | M33: =INDEX(Vendor_Master!$C:$C,MATCH(B33,Vendor_Master!$A:$A,0)) -> 45 | N33: =IF(H33>Assumptions!$B$4,"Large","") -> Large | O33: =INDEX(Vendor_Master!$B:$B,MATCH(B33,Vendor_Master!$A:$A,0)) -> Professional Fees | P33: =MONTH(D33) -> 3
A34: INV-1033 | B34: SafeGuard Fire & Safety | C34: Retail Plaza | D34: 2026-03-04 | E34: 2026-04-03 | F34: 40487.58 | G34: 7287.76 | H34: 47775.34 | I34: Paid | J34: 2026-03-15 | K34: =VLOOKUP(B34,Vendor_Master!$A:$C,3,FALSE()) -> 30 | L34: =_xlfn.XLOOKUP(B34,Vendor_Master!A:A,Vendor_Master!C:C) -> 30 | M34: =INDEX(Vendor_Master!$C:$C,MATCH(B34,Vendor_Master!$A:$A,0)) -> 30 | N34: =IF(H34>Assumptions!$B$4,"Large","") | O34: =INDEX(Vendor_Master!$B:$B,MATCH(B34,Vendor_Master!$A:$A,0)) -> Maintenance | P34: =MONTH(D34) -> 3
A35: INV-1034 | B35: Reliable Repairs Co | C35: Tower B | D35: 2026-02-26 | E35: 2026-03-28 | F35: 59182.86 | G35: 10652.91 | H35: 69835.77 | I35: Paid | J35: 2026-02-27 | K35: =VLOOKUP(B35,Vendor_Master!$A:$C,3,FALSE()) -> 30 | L35: =_xlfn.XLOOKUP(B35,Vendor_Master!A:A,Vendor_Master!C:C) -> 30 | M35: =INDEX(Vendor_Master!$C:$C,MATCH(B35,Vendor_Master!$A:$A,0)) -> 30 | N35: =IF(H35>Assumptions!$B$4,"Large","") | O35: =INDEX(Vendor_Master!$B:$B,MATCH(B35,Vendor_Master!$A:$A,0)) -> Repairs | P35: =MONTH(D35) -> 2
A36: INV-1035 | B36: Apex Security Solutions | C36: Tower B | D36: 2026-03-20 | E36: 2026-04-19 | F36: 62905.96 | G36: 11323.07 | H36: 74229.03 | I36: Paid | J36: 2026-03-21 | K36: =VLOOKUP(B36,Vendor_Master!$A:$C,3,FALSE()) -> 30 | L36: =_xlfn.XLOOKUP(B36,Vendor_Master!A:A,Vendor_Master!C:C) -> 30 | M36: =INDEX(Vendor_Master!$C:$C,MATCH(B36,Vendor_Master!$A:$A,0)) -> 30 | N36: =IF(H36>Assumptions!$B$4,"Large","") -> Large | O36: =INDEX(Vendor_Master!$B:$B,MATCH(B36,Vendor_Master!$A:$A,0)) -> Security | P36: =MONTH(D36) -> 3
A37: INV-1036 | B37: Reliable Repairs Co | C37: Commercial Block | D37: 2026-02-28 | E37: 2026-03-30 | F37: 52731.58 | G37: 9491.68 | H37: 62223.26 | I37: Paid | J37: 2026-03-10 | K37: =VLOOKUP(B37,Vendor_Master!$A:$C,3,FALSE()) -> 30 | L37: =_xlfn.XLOOKUP(B37,Vendor_Master!A:A,Vendor_Master!C:C) -> 30 | M37: =INDEX(Vendor_Master!$C:$C,MATCH(B37,Vendor_Master!$A:$A,0)) -> 30 | N37: =IF(H37>Assumptions!$B$4,"Large","") | O37: =INDEX(Vendor_Master!$B:$B,MATCH(B37,Vendor_Master!$A:$A,0)) -> Repairs | P37: =MONTH(D37) -> 2
A38: INV-1037 | B38: Nexus Professional Consultants | C38: Retail Plaza | D38: 2026-03-02 | E38: 2026-04-16 | F38: 70931.67 | G38: 12767.7 | H38: 83699.37 | I38: Paid | J38: 2026-03-29 | K38: =VLOOKUP(B38,Vendor_Master!$A:$C,3,FALSE()) -> 45 | L38: =_xlfn.XLOOKUP(B38,Vendor_Master!A:A,Vendor_Master!C:C) -> 45 | M38: =INDEX(Vendor_Master!$C:$C,MATCH(B38,Vendor_Master!$A:$A,0)) -> 45 | N38: =IF(H38>Assumptions!$B$4,"Large","") -> Large | O38: =INDEX(Vendor_Master!$B:$B,MATCH(B38,Vendor_Master!$A:$A,0)) -> Professional Fees | P38: =MONTH(D38) -> 3
A39: INV-1038 | B39: Capital Insurance Brokers | C39: Retail Plaza | D39: 2026-03-04 | E39: 2026-04-18 | F39: 16206.34 | G39: 2917.14 | H39: 19123.48 | I39: Paid | J39: 2026-03-27 | K39: =VLOOKUP(B39,Vendor_Master!$A:$C,3,FALSE()) -> 45 | L39: =_xlfn.XLOOKUP(B39,Vendor_Master!A:A,Vendor_Master!C:C) -> 45 | M39: =INDEX(Vendor_Master!$C:$C,MATCH(B39,Vendor_Master!$A:$A,0)) -> 45 | N39: =IF(H39>Assumptions!$B$4,"Large","") | O39: =INDEX(Vendor_Master!$B:$B,MATCH(B39,Vendor_Master!$A:$A,0)) -> Insurance | P39: =MONTH(D39) -> 3
A40: INV-1039 | B40: BrightWay Office Supplies | C40: Tower A | D40: 2026-03-25 | E40: 2026-04-09 | F40: 71429.6 | G40: 12857.33 | H40: 84286.93 | I40: Paid | J40: 2026-04-14 | K40: =VLOOKUP(B40,Vendor_Master!$A:$C,3,FALSE()) -> 15 | L40: =_xlfn.XLOOKUP(B40,Vendor_Master!A:A,Vendor_Master!C:C) -> 15 | M40: =INDEX(Vendor_Master!$C:$C,MATCH(B40,Vendor_Master!$A:$A,0)) -> 15 | N40: =IF(H40>Assumptions!$B$4,"Large","") -> Large | O40: =INDEX(Vendor_Master!$B:$B,MATCH(B40,Vendor_Master!$A:$A,0)) -> Office Supplies | P40: =MONTH(D40) -> 3
A41: INV-1040 | B41: Apex Security Solutions | C41: Retail Plaza | D41: 2026-03-19 | E41: 2026-04-18 | F41: 24668.34 | G41: 4440.3 | H41: 29108.64 | I41: Paid | J41: 2026-03-27 | K41: =VLOOKUP(B41,Vendor_Master!$A:$C,3,FALSE()) -> 30 | L41: =_xlfn.XLOOKUP(B41,Vendor_Master!A:A,Vendor_Master!C:C) -> 30 | M41: =INDEX(Vendor_Master!$C:$C,MATCH(B41,Vendor_Master!$A:$A,0)) -> 30 | N41: =IF(H41>Assumptions!$B$4,"Large","") | O41: =INDEX(Vendor_Master!$B:$B,MATCH(B41,Vendor_Master!$A:$A,0)) -> Security | P41: =MONTH(D41) -> 3
A42: INV-1041 | B42: Delhi Power Utilities Pvt Ltd | C42: Tower A | D42: 2026-03-26 | E42: 2026-04-10 | F42: 29733.16 | G42: 5351.97 | H42: 35085.13 | I42: Paid | J42: 2026-04-09 | K42: =VLOOKUP(B42,Vendor_Master!$A:$C,3,FALSE()) -> 15 | L42: =_xlfn.XLOOKUP(B42,Vendor_Master!A:A,Vendor_Master!C:C) -> 15 | M42: =INDEX(Vendor_Master!$C:$C,MATCH(B42,Vendor_Master!$A:$A,0)) -> 15 | N42: =IF(H42>Assumptions!$B$4,"Large","") | O42: =INDEX(Vendor_Master!$B:$B,MATCH(B42,Vendor_Master!$A:$A,0)) -> Utilities | P42: =MONTH(D42) -> 3
A43: INV-1042 | B43: Apex Security Solutions | C43: Tower A | D43: 2026-03-13 | E43: 2026-04-12 | F43: 64736.61 | G43: 11652.59 | H43: 76389.2 | I43: Overdue | K43: =VLOOKUP(B43,Vendor_Master!$A:$C,3,FALSE()) -> 30 | L43: =_xlfn.XLOOKUP(B43,Vendor_Master!A:A,Vendor_Master!C:C) -> 30 | M43: =INDEX(Vendor_Master!$C:$C,MATCH(B43,Vendor_Master!$A:$A,0)) -> 30 | N43: =IF(H43>Assumptions!$B$4,"Large","") -> Large | O43: =INDEX(Vendor_Master!$B:$B,MATCH(B43,Vendor_Master!$A:$A,0)) -> Security | P43: =MONTH(D43) -> 3
A44: INV-1043 | B44: GreenScape Landscaping | C44: Retail Plaza | D44: 2026-03-17 | E44: 2026-04-16 | F44: 43358.02 | G44: 7804.44 | H44: 51162.46 | I44: Paid | J44: 2026-04-08 | K44: =VLOOKUP(B44,Vendor_Master!$A:$C,3,FALSE()) -> 30 | L44: =_xlfn.XLOOKUP(B44,Vendor_Master!A:A,Vendor_Master!C:C) -> 30 | M44: =INDEX(Vendor_Master!$C:$C,MATCH(B44,Vendor_Master!$A:$A,0)) -> 30 | N44: =IF(H44>Assumptions!$B$4,"Large","") | O44: =INDEX(Vendor_Master!$B:$B,MATCH(B44,Vendor_Master!$A:$A,0)) -> Landscaping | P44: =MONTH(D44) -> 3
A45: INV-1044 | B45: Shree Maintenance Services | C45: Retail Plaza | D45: 2026-03-17 | E45: 2026-04-16 | F45: 40970.66 | G45: 7374.72 | H45: 48345.38 | I45: Paid | J45: 2026-04-12 | K45: =VLOOKUP(B45,Vendor_Master!$A:$C,3,FALSE()) -> 30 | L45: =_xlfn.XLOOKUP(B45,Vendor_Master!A:A,Vendor_Master!C:C) -> 30 | M45: =INDEX(Vendor_Master!$C:$C,MATCH(B45,Vendor_Master!$A:$A,0)) -> 30 | N45: =IF(H45>Assumptions!$B$4,"Large","") | O45: =INDEX(Vendor_Master!$B:$B,MATCH(B45,Vendor_Master!$A:$A,0)) -> Maintenance | P45: =MONTH(D45) -> 3
A46: INV-1045 | B46: Delhi Power Utilities Pvt Ltd | C46: Retail Plaza | D46: 2026-03-25 | E46: 2026-04-09 | F46: 68603.46 | G46: 12348.62 | H46: 80952.08 | I46: Paid | J46: 2026-03-31 | K46: =VLOOKUP(B46,Vendor_Master!$A:$C,3,FALSE()) -> 15 | L46: =_xlfn.XLOOKUP(B46,Vendor_Master!A:A,Vendor_Master!C:C) -> 15 | M46: =INDEX(Vendor_Master!$C:$C,MATCH(B46,Vendor_Master!$A:$A,0)) -> 15 | N46: =IF(H46>Assumptions!$B$4,"Large","") -> Large | O46: =INDEX(Vendor_Master!$B:$B,MATCH(B46,Vendor_Master!$A:$A,0)) -> Utilities | P46: =MONTH(D46) -> 3
A47: INV-1046 | B47: GreenScape Landscaping | C47: Tower A | D47: 2026-03-13 | E47: 2026-04-12 | F47: 58388.69 | G47: 10509.96 | H47: 68898.65 | I47: Paid | J47: 2026-03-14 | K47: =VLOOKUP(B47,Vendor_Master!$A:$C,3,FALSE()) -> 30 | L47: =_xlfn.XLOOKUP(B47,Vendor_Master!A:A,Vendor_Master!C:C) -> 30 | M47: =INDEX(Vendor_Master!$C:$C,MATCH(B47,Vendor_Master!$A:$A,0)) -> 30 | N47: =IF(H47>Assumptions!$B$4,"Large","") | O47: =INDEX(Vendor_Master!$B:$B,MATCH(B47,Vendor_Master!$A:$A,0)) -> Landscaping | P47: =MONTH(D47) -> 3
A48: INV-1047 | B48: Shree Maintenance Services | C48: Tower B | D48: 2026-03-30 | E48: 2026-04-29 | F48: 49480.6 | G48: 8906.51 | H48: 58387.11 | I48: Paid | J48: 2026-04-28 | K48: =VLOOKUP(B48,Vendor_Master!$A:$C,3,FALSE()) -> 30 | L48: =_xlfn.XLOOKUP(B48,Vendor_Master!A:A,Vendor_Master!C:C) -> 30 | M48: =INDEX(Vendor_Master!$C:$C,MATCH(B48,Vendor_Master!$A:$A,0)) -> 30 | N48: =IF(H48>Assumptions!$B$4,"Large","") | O48: =INDEX(Vendor_Master!$B:$B,MATCH(B48,Vendor_Master!$A:$A,0)) -> Maintenance | P48: =MONTH(D48) -> 3
A49: INV-1048 | B49: Clean & Clear Housekeeping | C49: Tower B | D49: 2026-03-28 | E49: 2026-04-12 | F49: 59768.05 | G49: 10758.25 | H49: 70526.3 | I49: Paid | J49: 2026-04-12 | K49: =VLOOKUP(B49,Vendor_Master!$A:$C,3,FALSE()) -> 15 | L49: =_xlfn.XLOOKUP(B49,Vendor_Master!A:A,Vendor_Master!C:C) -> 15 | M49: =INDEX(Vendor_Master!$C:$C,MATCH(B49,Vendor_Master!$A:$A,0)) -> 15 | N49: =IF(H49>Assumptions!$B$4,"Large","") -> Large | O49: =INDEX(Vendor_Master!$B:$B,MATCH(B49,Vendor_Master!$A:$A,0)) -> Housekeeping | P49: =MONTH(D49) -> 3
A50: INV-1049 | B50: GreenScape Landscaping | C50: Tower A | D50: 2026-04-13 | E50: 2026-05-13 | F50: 59723.17 | G50: 10750.17 | H50: 70473.34 | I50: Paid | J50: 2026-05-17 | K50: =VLOOKUP(B50,Vendor_Master!$A:$C,3,FALSE()) -> 30 | L50: =_xlfn.XLOOKUP(B50,Vendor_Master!A:A,Vendor_Master!C:C) -> 30 | M50: =INDEX(Vendor_Master!$C:$C,MATCH(B50,Vendor_Master!$A:$A,0)) -> 30 | N50: =IF(H50>Assumptions!$B$4,"Large","") -> Large | O50: =INDEX(Vendor_Master!$B:$B,MATCH(B50,Vendor_Master!$A:$A,0)) -> Landscaping | P50: =MONTH(D50) -> 4
A51: INV-1050 | B51: UrbanEdge Marketing | C51: Commercial Block | D51: 2026-04-11 | E51: 2026-05-11 | F51: 35524.18 | G51: 6394.35 | H51: 41918.53 | I51: Paid | J51: 2026-04-28 | K51: =VLOOKUP(B51,Vendor_Master!$A:$C,3,FALSE()) -> 30 | L51: =_xlfn.XLOOKUP(B51,Vendor_Master!A:A,Vendor_Master!C:C) -> 30 | M51: =INDEX(Vendor_Master!$C:$C,MATCH(B51,Vendor_Master!$A:$A,0)) -> 30 | N51: =IF(H51>Assumptions!$B$4,"Large","") | O51: =INDEX(Vendor_Master!$B:$B,MATCH(B51,Vendor_Master!$A:$A,0)) -> Marketing | P51: =MONTH(D51) -> 4
A52: INV-1051 | B52: GreenScape Landscaping | C52: Commercial Block | D52: 2026-04-03 | E52: 2026-05-03 | F52: 42433.37 | G52: 7638.01 | H52: 50071.38 | I52: Paid | J52: 2026-04-04 | K52: =VLOOKUP(B52,Vendor_Master!$A:$C,3,FALSE()) -> 30 | L52: =_xlfn.XLOOKUP(B52,Vendor_Master!A:A,Vendor_Master!C:C) -> 30 | M52: =INDEX(Vendor_Master!$C:$C,MATCH(B52,Vendor_Master!$A:$A,0)) -> 30 | N52: =IF(H52>Assumptions!$B$4,"Large","") | O52: =INDEX(Vendor_Master!$B:$B,MATCH(B52,Vendor_Master!$A:$A,0)) -> Landscaping | P52: =MONTH(D52) -> 4
A53: INV-1052 | B53: Shree Maintenance Services | C53: Tower A | D53: 2026-04-09 | E53: 2026-05-09 | F53: 62040.86 | G53: 11167.35 | H53: 73208.21 | I53: Paid | J53: 2026-04-19 | K53: =VLOOKUP(B53,Vendor_Master!$A:$C,3,FALSE()) -> 30 | L53: =_xlfn.XLOOKUP(B53,Vendor_Master!A:A,Vendor_Master!C:C) -> 30 | M53: =INDEX(Vendor_Master!$C:$C,MATCH(B53,Vendor_Master!$A:$A,0)) -> 30 | N53: =IF(H53>Assumptions!$B$4,"Large","") -> Large | O53: =INDEX(Vendor_Master!$B:$B,MATCH(B53,Vendor_Master!$A:$A,0)) -> Maintenance | P53: =MONTH(D53) -> 4
A54: INV-1053 | B54: Nexus Professional Consultants | C54: Commercial Block | D54: 2026-04-03 | E54: 2026-05-18 | F54: 19523.72 | G54: 3514.27 | H54: 23037.99 | I54: Overdue | K54: =VLOOKUP(B54,Vendor_Master!$A:$C,3,FALSE()) -> 45 | L54: =_xlfn.XLOOKUP(B54,Vendor_Master!A:A,Vendor_Master!C:C) -> 45 | M54: =INDEX(Vendor_Master!$C:$C,MATCH(B54,Vendor_Master!$A:$A,0)) -> 45 | N54: =IF(H54>Assumptions!$B$4,"Large","") | O54: =INDEX(Vendor_Master!$B:$B,MATCH(B54,Vendor_Master!$A:$A,0)) -> Professional Fees | P54: =MONTH(D54) -> 4
A55: INV-1054 | B55: Reliable Repairs Co | C55: Commercial Block | D55: 2026-04-18 | E55: 2026-05-18 | F55: 21723.97 | G55: 3910.31 | H55: 25634.28 | I55: Paid | J55: 2026-05-18 | K55: =VLOOKUP(B55,Vendor_Master!$A:$C,3,FALSE()) -> 30 | L55: =_xlfn.XLOOKUP(B55,Vendor_Master!A:A,Vendor_Master!C:C) -> 30 | M55: =INDEX(Vendor_Master!$C:$C,MATCH(B55,Vendor_Master!$A:$A,0)) -> 30 | N55: =IF(H55>Assumptions!$B$4,"Large","") | O55: =INDEX(Vendor_Master!$B:$B,MATCH(B55,Vendor_Master!$A:$A,0)) -> Repairs | P55: =MONTH(D55) -> 4
A56: INV-1055 | B56: Shree Maintenance Services | C56: Commercial Block | D56: 2026-04-30 | E56: 2026-05-30 | F56: 79088.06 | G56: 14235.85 | H56: 93323.91 | I56: Overdue | K56: =VLOOKUP(B56,Vendor_Master!$A:$C,3,FALSE()) -> 30 | L56: =_xlfn.XLOOKUP(B56,Vendor_Master!A:A,Vendor_Master!C:C) -> 30 | M56: =INDEX(Vendor_Master!$C:$C,MATCH(B56,Vendor_Master!$A:$A,0)) -> 30 | N56: =IF(H56>Assumptions!$B$4,"Large","") -> Large | O56: =INDEX(Vendor_Master!$B:$B,MATCH(B56,Vendor_Master!$A:$A,0)) -> Maintenance | P56: =MONTH(D56) -> 4
A57: INV-1056 | B57: Apex Security Solutions | C57: Tower A | D57: 2026-04-13 | E57: 2026-05-13 | F57: 31008.54 | G57: 5581.54 | H57: 36590.08 | I57: Paid | J57: 2026-04-19 | K57: =VLOOKUP(B57,Vendor_Master!$A:$C,3,FALSE()) -> 30 | L57: =_xlfn.XLOOKUP(B57,Vendor_Master!A:A,Vendor_Master!C:C) -> 30 | M57: =INDEX(Vendor_Master!$C:$C,MATCH(B57,Vendor_Master!$A:$A,0)) -> 30 | N57: =IF(H57>Assumptions!$B$4,"Large","") | O57: =INDEX(Vendor_Master!$B:$B,MATCH(B57,Vendor_Master!$A:$A,0)) -> Security | P57: =MONTH(D57) -> 4
A58: INV-1057 | B58: Delhi Power Utilities Pvt Ltd | C58: Commercial Block | D58: 2026-04-18 | E58: 2026-05-03 | F58: 60620.19 | G58: 10911.63 | H58: 71531.82 | I58: Paid | J58: 2026-05-05 | K58: =VLOOKUP(B58,Vendor_Master!$A:$C,3,FALSE()) -> 15 | L58: =_xlfn.XLOOKUP(B58,Vendor_Master!A:A,Vendor_Master!C:C) -> 15 | M58: =INDEX(Vendor_Master!$C:$C,MATCH(B58,Vendor_Master!$A:$A,0)) -> 15 | N58: =IF(H58>Assumptions!$B$4,"Large","") -> Large | O58: =INDEX(Vendor_Master!$B:$B,MATCH(B58,Vendor_Master!$A:$A,0)) -> Utilities | P58: =MONTH(D58) -> 4
A59: INV-1058 | B59: Delhi Power Utilities Pvt Ltd | C59: Tower A | D59: 2026-04-25 | E59: 2026-05-10 | F59: 50502.27 | G59: 9090.41 | H59: 59592.68 | I59: Paid | J59: 2026-05-05 | K59: =VLOOKUP(B59,Vendor_Master!$A:$C,3,FALSE()) -> 15 | L59: =_xlfn.XLOOKUP(B59,Vendor_Master!A:A,Vendor_Master!C:C) -> 15 | M59: =INDEX(Vendor_Master!$C:$C,MATCH(B59,Vendor_Master!$A:$A,0)) -> 15 | N59: =IF(H59>Assumptions!$B$4,"Large","") | O59: =INDEX(Vendor_Master!$B:$B,MATCH(B59,Vendor_Master!$A:$A,0)) -> Utilities | P59: =MONTH(D59) -> 4
A60: INV-1059 | B60: Delhi Power Utilities Pvt Ltd | C60: Tower B | D60: 2026-04-10 | E60: 2026-04-25 | F60: 8308.47 | G60: 1495.52 | H60: 9803.99 | I60: Paid | J60: 2026-04-15 | K60: =VLOOKUP(B60,Vendor_Master!$A:$C,3,FALSE()) -> 15 | L60: =_xlfn.XLOOKUP(B60,Vendor_Master!A:A,Vendor_Master!C:C) -> 15 | M60: =INDEX(Vendor_Master!$C:$C,MATCH(B60,Vendor_Master!$A:$A,0)) -> 15 | N60: =IF(H60>Assumptions!$B$4,"Large","") | O60: =INDEX(Vendor_Master!$B:$B,MATCH(B60,Vendor_Master!$A:$A,0)) -> Utilities | P60: =MONTH(D60) -> 4
A61: INV-1060 | B61: Clean & Clear Housekeeping | C61: Retail Plaza | D61: 2026-05-02 | E61: 2026-05-17 | F61: 46439.69 | G61: 8359.14 | H61: 54798.83 | I61: Paid | J61: 2026-05-03 | K61: =VLOOKUP(B61,Vendor_Master!$A:$C,3,FALSE()) -> 15 | L61: =_xlfn.XLOOKUP(B61,Vendor_Master!A:A,Vendor_Master!C:C) -> 15 | M61: =INDEX(Vendor_Master!$C:$C,MATCH(B61,Vendor_Master!$A:$A,0)) -> 15 | N61: =IF(H61>Assumptions!$B$4,"Large","") | O61: =INDEX(Vendor_Master!$B:$B,MATCH(B61,Vendor_Master!$A:$A,0)) -> Housekeeping | P61: =MONTH(D61) -> 5
A62: INV-1061 | B62: Crystal Water Treatment | C62: Commercial Block | D62: 2026-04-27 | E62: 2026-05-12 | F62: 55466.36 | G62: 9983.94 | H62: 65450.3 | I62: Paid | J62: 2026-04-28 | K62: =VLOOKUP(B62,Vendor_Master!$A:$C,3,FALSE()) -> 15 | L62: =_xlfn.XLOOKUP(B62,Vendor_Master!A:A,Vendor_Master!C:C) -> 15 | M62: =INDEX(Vendor_Master!$C:$C,MATCH(B62,Vendor_Master!$A:$A,0)) -> 15 | N62: =IF(H62>Assumptions!$B$4,"Large","") | O62: =INDEX(Vendor_Master!$B:$B,MATCH(B62,Vendor_Master!$A:$A,0)) -> Utilities | P62: =MONTH(D62) -> 4
A63: INV-1062 | B63: Capital Insurance Brokers | C63: Commercial Block | D63: 2026-04-27 | E63: 2026-06-11 | F63: 11639.11 | G63: 2095.04 | H63: 13734.15 | I63: Overdue | K63: =VLOOKUP(B63,Vendor_Master!$A:$C,3,FALSE()) -> 45 | L63: =_xlfn.XLOOKUP(B63,Vendor_Master!A:A,Vendor_Master!C:C) -> 45 | M63: =INDEX(Vendor_Master!$C:$C,MATCH(B63,Vendor_Master!$A:$A,0)) -> 45 | N63: =IF(H63>Assumptions!$B$4,"Large","") | O63: =INDEX(Vendor_Master!$B:$B,MATCH(B63,Vendor_Master!$A:$A,0)) -> Insurance | P63: =MONTH(D63) -> 4
A64: INV-1063 | B64: Shree Maintenance Services | C64: Tower B | D64: 2026-05-04 | E64: 2026-06-03 | F64: 26276.66 | G64: 4729.8 | H64: 31006.46 | I64: Paid | J64: 2026-05-23 | K64: =VLOOKUP(B64,Vendor_Master!$A:$C,3,FALSE()) -> 30 | L64: =_xlfn.XLOOKUP(B64,Vendor_Master!A:A,Vendor_Master!C:C) -> 30 | M64: =INDEX(Vendor_Master!$C:$C,MATCH(B64,Vendor_Master!$A:$A,0)) -> 30 | N64: =IF(H64>Assumptions!$B$4,"Large","") | O64: =INDEX(Vendor_Master!$B:$B,MATCH(B64,Vendor_Master!$A:$A,0)) -> Maintenance | P64: =MONTH(D64) -> 5
A65: INV-1064 | B65: Nexus Professional Consultants | C65: Tower B | D65: 2026-05-20 | E65: 2026-07-04 | F65: 43354.83 | G65: 7803.87 | H65: 51158.7 | I65: Paid | J65: 2026-05-30 | K65: =VLOOKUP(B65,Vendor_Master!$A:$C,3,FALSE()) -> 45 | L65: =_xlfn.XLOOKUP(B65,Vendor_Master!A:A,Vendor_Master!C:C) -> 45 | M65: =INDEX(Vendor_Master!$C:$C,MATCH(B65,Vendor_Master!$A:$A,0)) -> 45 | N65: =IF(H65>Assumptions!$B$4,"Large","") | O65: =INDEX(Vendor_Master!$B:$B,MATCH(B65,Vendor_Master!$A:$A,0)) -> Professional Fees | P65: =MONTH(D65) -> 5
A66: INV-1065 | B66: Clean & Clear Housekeeping | C66: Retail Plaza | D66: 2026-05-18 | E66: 2026-06-02 | F66: 78537.14 | G66: 14136.69 | H66: 92673.83 | I66: Paid | J66: 2026-06-07 | K66: =VLOOKUP(B66,Vendor_Master!$A:$C,3,FALSE()) -> 15 | L66: =_xlfn.XLOOKUP(B66,Vendor_Master!A:A,Vendor_Master!C:C) -> 15 | M66: =INDEX(Vendor_Master!$C:$C,MATCH(B66,Vendor_Master!$A:$A,0)) -> 15 | N66: =IF(H66>Assumptions!$B$4,"Large","") -> Large | O66: =INDEX(Vendor_Master!$B:$B,MATCH(B66,Vendor_Master!$A:$A,0)) -> Housekeeping | P66: =MONTH(D66) -> 5
A67: INV-1066 | B67: Reliable Repairs Co | C67: Tower B | D67: 2026-05-18 | E67: 2026-06-17 | F67: 88980.98 | G67: 16016.58 | H67: 104997.56 | I67: Paid | J67: 2026-05-21 | K67: =VLOOKUP(B67,Vendor_Master!$A:$C,3,FALSE()) -> 30 | L67: =_xlfn.XLOOKUP(B67,Vendor_Master!A:A,Vendor_Master!C:C) -> 30 | M67: =INDEX(Vendor_Master!$C:$C,MATCH(B67,Vendor_Master!$A:$A,0)) -> 30 | N67: =IF(H67>Assumptions!$B$4,"Large","") -> Large | O67: =INDEX(Vendor_Master!$B:$B,MATCH(B67,Vendor_Master!$A:$A,0)) -> Repairs | P67: =MONTH(D67) -> 5
A68: INV-1067 | B68: Shree Maintenance Services | C68: Tower B | D68: 2026-06-03 | E68: 2026-07-03 | F68: 48950.03 | G68: 8811.01 | H68: 57761.04 | I68: Paid | J68: 2026-06-27 | K68: =VLOOKUP(B68,Vendor_Master!$A:$C,3,FALSE()) -> 30 | L68: =_xlfn.XLOOKUP(B68,Vendor_Master!A:A,Vendor_Master!C:C) -> 30 | M68: =INDEX(Vendor_Master!$C:$C,MATCH(B68,Vendor_Master!$A:$A,0)) -> 30 | N68: =IF(H68>Assumptions!$B$4,"Large","") | O68: =INDEX(Vendor_Master!$B:$B,MATCH(B68,Vendor_Master!$A:$A,0)) -> Maintenance | P68: =MONTH(D68) -> 6
A69: INV-1068 | B69: Reliable Repairs Co | C69: Tower B | D69: 2026-05-16 | E69: 2026-06-15 | F69: 79386.67 | G69: 14289.6 | H69: 93676.27 | I69: Paid | J69: 2026-05-25 | K69: =VLOOKUP(B69,Vendor_Master!$A:$C,3,FALSE()) -> 30 | L69: =_xlfn.XLOOKUP(B69,Vendor_Master!A:A,Vendor_Master!C:C) -> 30 | M69: =INDEX(Vendor_Master!$C:$C,MATCH(B69,Vendor_Master!$A:$A,0)) -> 30 | N69: =IF(H69>Assumptions!$B$4,"Large","") -> Large | O69: =INDEX(Vendor_Master!$B:$B,MATCH(B69,Vendor_Master!$A:$A,0)) -> Repairs | P69: =MONTH(D69) -> 5
A70: INV-1069 | B70: Capital Insurance Brokers | C70: Tower A | D70: 2026-05-17 | E70: 2026-07-01 | F70: 32238.47 | G70: 5802.92 | H70: 38041.39 | I70: Paid | J70: 2026-05-29 | K70: =VLOOKUP(B70,Vendor_Master!$A:$C,3,FALSE()) -> 45 | L70: =_xlfn.XLOOKUP(B70,Vendor_Master!A:A,Vendor_Master!C:C) -> 45 | M70: =INDEX(Vendor_Master!$C:$C,MATCH(B70,Vendor_Master!$A:$A,0)) -> 45 | N70: =IF(H70>Assumptions!$B$4,"Large","") | O70: =INDEX(Vendor_Master!$B:$B,MATCH(B70,Vendor_Master!$A:$A,0)) -> Insurance | P70: =MONTH(D70) -> 5
A71: INV-1070 | B71: Reliable Repairs Co | C71: Commercial Block | D71: 2026-05-27 | E71: 2026-06-26 | F71: 52318.29 | G71: 9417.29 | H71: 61735.58 | I71: Overdue | K71: =VLOOKUP(B71,Vendor_Master!$A:$C,3,FALSE()) -> 30 | L71: =_xlfn.XLOOKUP(B71,Vendor_Master!A:A,Vendor_Master!C:C) -> 30 | M71: =INDEX(Vendor_Master!$C:$C,MATCH(B71,Vendor_Master!$A:$A,0)) -> 30 | N71: =IF(H71>Assumptions!$B$4,"Large","") | O71: =INDEX(Vendor_Master!$B:$B,MATCH(B71,Vendor_Master!$A:$A,0)) -> Repairs | P71: =MONTH(D71) -> 5
A72: INV-1071 | B72: Apex Security Solutions | C72: Commercial Block | D72: 2026-05-15 | E72: 2026-06-14 | F72: 23535.4 | G72: 4236.37 | H72: 27771.77 | I72: Paid | J72: 2026-06-19 | K72: =VLOOKUP(B72,Vendor_Master!$A:$C,3,FALSE()) -> 30 | L72: =_xlfn.XLOOKUP(B72,Vendor_Master!A:A,Vendor_Master!C:C) -> 30 | M72: =INDEX(Vendor_Master!$C:$C,MATCH(B72,Vendor_Master!$A:$A,0)) -> 30 | N72: =IF(H72>Assumptions!$B$4,"Large","") | O72: =INDEX(Vendor_Master!$B:$B,MATCH(B72,Vendor_Master!$A:$A,0)) -> Security | P72: =MONTH(D72) -> 5
A73: INV-1072 | B73: Capital Insurance Brokers | C73: Commercial Block | D73: 2026-05-18 | E73: 2026-07-02 | F73: 71383.42 | G73: 12849.02 | H73: 84232.44 | I73: Pending | K73: =VLOOKUP(B73,Vendor_Master!$A:$C,3,FALSE()) -> 45 | L73: =_xlfn.XLOOKUP(B73,Vendor_Master!A:A,Vendor_Master!C:C) -> 45 | M73: =INDEX(Vendor_Master!$C:$C,MATCH(B73,Vendor_Master!$A:$A,0)) -> 45 | N73: =IF(H73>Assumptions!$B$4,"Large","") -> Large | O73: =INDEX(Vendor_Master!$B:$B,MATCH(B73,Vendor_Master!$A:$A,0)) -> Insurance | P73: =MONTH(D73) -> 5
A74: INV-1073 | B74: Nexus Professional Consultants | C74: Tower B | D74: 2026-05-10 | E74: 2026-06-24 | F74: 41512 | G74: 7472.16 | H74: 48984.16 | I74: Paid | J74: 2026-06-21 | K74: =VLOOKUP(B74,Vendor_Master!$A:$C,3,FALSE()) -> 45 | L74: =_xlfn.XLOOKUP(B74,Vendor_Master!A:A,Vendor_Master!C:C) -> 45 | M74: =INDEX(Vendor_Master!$C:$C,MATCH(B74,Vendor_Master!$A:$A,0)) -> 45 | N74: =IF(H74>Assumptions!$B$4,"Large","") | O74: =INDEX(Vendor_Master!$B:$B,MATCH(B74,Vendor_Master!$A:$A,0)) -> Professional Fees | P74: =MONTH(D74) -> 5
A75: INV-1074 | B75: Capital Insurance Brokers | C75: Tower B | D75: 2026-05-07 | E75: 2026-06-21 | F75: 53233.07 | G75: 9581.95 | H75: 62815.02 | I75: Paid | J75: 2026-05-08 | K75: =VLOOKUP(B75,Vendor_Master!$A:$C,3,FALSE()) -> 45 | L75: =_xlfn.XLOOKUP(B75,Vendor_Master!A:A,Vendor_Master!C:C) -> 45 | M75: =INDEX(Vendor_Master!$C:$C,MATCH(B75,Vendor_Master!$A:$A,0)) -> 45 | N75: =IF(H75>Assumptions!$B$4,"Large","") | O75: =INDEX(Vendor_Master!$B:$B,MATCH(B75,Vendor_Master!$A:$A,0)) -> Insurance | P75: =MONTH(D75) -> 5
A76: INV-1075 | B76: SafeGuard Fire & Safety | C76: Tower A | D76: 2026-05-17 | E76: 2026-06-16 | F76: 62214.52 | G76: 11198.61 | H76: 73413.13 | I76: Paid | J76: 2026-06-02 | K76: =VLOOKUP(B76,Vendor_Master!$A:$C,3,FALSE()) -> 30 | L76: =_xlfn.XLOOKUP(B76,Vendor_Master!A:A,Vendor_Master!C:C) -> 30 | M76: =INDEX(Vendor_Master!$C:$C,MATCH(B76,Vendor_Master!$A:$A,0)) -> 30 | N76: =IF(H76>Assumptions!$B$4,"Large","") -> Large | O76: =INDEX(Vendor_Master!$B:$B,MATCH(B76,Vendor_Master!$A:$A,0)) -> Maintenance | P76: =MONTH(D76) -> 5
A77: INV-1076 | B77: Delhi Power Utilities Pvt Ltd | C77: Retail Plaza | D77: 2026-06-11 | E77: 2026-06-26 | F77: 43530.18 | G77: 7835.43 | H77: 51365.61 | I77: Paid | J77: 2026-06-25 | K77: =VLOOKUP(B77,Vendor_Master!$A:$C,3,FALSE()) -> 15 | L77: =_xlfn.XLOOKUP(B77,Vendor_Master!A:A,Vendor_Master!C:C) -> 15 | M77: =INDEX(Vendor_Master!$C:$C,MATCH(B77,Vendor_Master!$A:$A,0)) -> 15 | N77: =IF(H77>Assumptions!$B$4,"Large","") | O77: =INDEX(Vendor_Master!$B:$B,MATCH(B77,Vendor_Master!$A:$A,0)) -> Utilities | P77: =MONTH(D77) -> 6
A78: INV-1077 | B78: Clean & Clear Housekeeping | C78: Retail Plaza | D78: 2026-05-27 | E78: 2026-06-11 | F78: 44578.83 | G78: 8024.19 | H78: 52603.02 | I78: Paid | J78: 2026-05-29 | K78: =VLOOKUP(B78,Vendor_Master!$A:$C,3,FALSE()) -> 15 | L78: =_xlfn.XLOOKUP(B78,Vendor_Master!A:A,Vendor_Master!C:C) -> 15 | M78: =INDEX(Vendor_Master!$C:$C,MATCH(B78,Vendor_Master!$A:$A,0)) -> 15 | N78: =IF(H78>Assumptions!$B$4,"Large","") | O78: =INDEX(Vendor_Master!$B:$B,MATCH(B78,Vendor_Master!$A:$A,0)) -> Housekeeping | P78: =MONTH(D78) -> 5
A79: INV-1078 | B79: UrbanEdge Marketing | C79: Tower A | D79: 2026-06-08 | E79: 2026-07-08 | F79: 34182.64 | G79: 6152.88 | H79: 40335.52 | I79: Pending | K79: =VLOOKUP(B79,Vendor_Master!$A:$C,3,FALSE()) -> 30 | L79: =_xlfn.XLOOKUP(B79,Vendor_Master!A:A,Vendor_Master!C:C) -> 30 | M79: =INDEX(Vendor_Master!$C:$C,MATCH(B79,Vendor_Master!$A:$A,0)) -> 30 | N79: =IF(H79>Assumptions!$B$4,"Large","") | O79: =INDEX(Vendor_Master!$B:$B,MATCH(B79,Vendor_Master!$A:$A,0)) -> Marketing | P79: =MONTH(D79) -> 6
A80: INV-1079 | B80: GreenScape Landscaping | C80: Commercial Block | D80: 2026-06-03 | E80: 2026-07-03 | F80: 76361.02 | G80: 13744.98 | H80: 90106 | I80: Pending | K80: =VLOOKUP(B80,Vendor_Master!$A:$C,3,FALSE()) -> 30 | L80: =_xlfn.XLOOKUP(B80,Vendor_Master!A:A,Vendor_Master!C:C) -> 30 | M80: =INDEX(Vendor_Master!$C:$C,MATCH(B80,Vendor_Master!$A:$A,0)) -> 30 | N80: =IF(H80>Assumptions!$B$4,"Large","") -> Large | O80: =INDEX(Vendor_Master!$B:$B,MATCH(B80,Vendor_Master!$A:$A,0)) -> Landscaping | P80: =MONTH(D80) -> 6
A81: INV-1080 | B81: BrightWay Office Supplies | C81: Retail Plaza | D81: 2026-06-11 | E81: 2026-06-26 | F81: 26592.02 | G81: 4786.56 | H81: 31378.58 | I81: Overdue | K81: =VLOOKUP(B81,Vendor_Master!$A:$C,3,FALSE()) -> 15 | L81: =_xlfn.XLOOKUP(B81,Vendor_Master!A:A,Vendor_Master!C:C) -> 15 | M81: =INDEX(Vendor_Master!$C:$C,MATCH(B81,Vendor_Master!$A:$A,0)) -> 15 | N81: =IF(H81>Assumptions!$B$4,"Large","") | O81: =INDEX(Vendor_Master!$B:$B,MATCH(B81,Vendor_Master!$A:$A,0)) -> Office Supplies | P81: =MONTH(D81) -> 6
A82: INV-1081 | B82: Crystal Water Treatment | C82: Commercial Block | D82: 2026-05-26 | E82: 2026-06-10 | F82: 65320.01 | G82: 11757.6 | H82: 77077.61 | I82: Paid | J82: 2026-06-12 | K82: =VLOOKUP(B82,Vendor_Master!$A:$C,3,FALSE()) -> 15 | L82: =_xlfn.XLOOKUP(B82,Vendor_Master!A:A,Vendor_Master!C:C) -> 15 | M82: =INDEX(Vendor_Master!$C:$C,MATCH(B82,Vendor_Master!$A:$A,0)) -> 15 | N82: =IF(H82>Assumptions!$B$4,"Large","") -> Large | O82: =INDEX(Vendor_Master!$B:$B,MATCH(B82,Vendor_Master!$A:$A,0)) -> Utilities | P82: =MONTH(D82) -> 5
A83: INV-1082 | B83: UrbanEdge Marketing | C83: Tower B | D83: 2026-05-31 | E83: 2026-06-30 | F83: 16124.69 | G83: 2902.44 | H83: 19027.13 | I83: Paid | J83: 2026-06-11 | K83: =VLOOKUP(B83,Vendor_Master!$A:$C,3,FALSE()) -> 30 | L83: =_xlfn.XLOOKUP(B83,Vendor_Master!A:A,Vendor_Master!C:C) -> 30 | M83: =INDEX(Vendor_Master!$C:$C,MATCH(B83,Vendor_Master!$A:$A,0)) -> 30 | N83: =IF(H83>Assumptions!$B$4,"Large","") | O83: =INDEX(Vendor_Master!$B:$B,MATCH(B83,Vendor_Master!$A:$A,0)) -> Marketing | P83: =MONTH(D83) -> 5
A84: INV-1083 | B84: GreenScape Landscaping | C84: Tower B | D84: 2026-05-25 | E84: 2026-06-24 | F84: 10125.01 | G84: 1822.5 | H84: 11947.51 | I84: Overdue | K84: =VLOOKUP(B84,Vendor_Master!$A:$C,3,FALSE()) -> 30 | L84: =_xlfn.XLOOKUP(B84,Vendor_Master!A:A,Vendor_Master!C:C) -> 30 | M84: =INDEX(Vendor_Master!$C:$C,MATCH(B84,Vendor_Master!$A:$A,0)) -> 30 | N84: =IF(H84>Assumptions!$B$4,"Large","") | O84: =INDEX(Vendor_Master!$B:$B,MATCH(B84,Vendor_Master!$A:$A,0)) -> Landscaping | P84: =MONTH(D84) -> 5
A85: INV-1084 | B85: UrbanEdge Marketing | C85: Retail Plaza | D85: 2026-06-17 | E85: 2026-07-17 | F85: 74858.57 | G85: 13474.54 | H85: 88333.11 | I85: Pending | K85: =VLOOKUP(B85,Vendor_Master!$A:$C,3,FALSE()) -> 30 | L85: =_xlfn.XLOOKUP(B85,Vendor_Master!A:A,Vendor_Master!C:C) -> 30 | M85: =INDEX(Vendor_Master!$C:$C,MATCH(B85,Vendor_Master!$A:$A,0)) -> 30 | N85: =IF(H85>Assumptions!$B$4,"Large","") -> Large | O85: =INDEX(Vendor_Master!$B:$B,MATCH(B85,Vendor_Master!$A:$A,0)) -> Marketing | P85: =MONTH(D85) -> 6
A86: INV-1085 | B86: SafeGuard Fire & Safety | C86: Retail Plaza | D86: 2026-06-08 | E86: 2026-07-08 | F86: 24915.87 | G86: 4484.86 | H86: 29400.73 | I86: Pending | K86: =VLOOKUP(B86,Vendor_Master!$A:$C,3,FALSE()) -> 30 | L86: =_xlfn.XLOOKUP(B86,Vendor_Master!A:A,Vendor_Master!C:C) -> 30 | M86: =INDEX(Vendor_Master!$C:$C,MATCH(B86,Vendor_Master!$A:$A,0)) -> 30 | N86: =IF(H86>Assumptions!$B$4,"Large","") | O86: =INDEX(Vendor_Master!$B:$B,MATCH(B86,Vendor_Master!$A:$A,0)) -> Maintenance | P86: =MONTH(D86) -> 6
A87: INV-1086 | B87: Clean & Clear Housekeeping | C87: Tower A | D87: 2026-06-24 | E87: 2026-07-09 | F87: 67823.15 | G87: 12208.17 | H87: 80031.32 | I87: Paid | J87: 2026-06-26 | K87: =VLOOKUP(B87,Vendor_Master!$A:$C,3,FALSE()) -> 15 | L87: =_xlfn.XLOOKUP(B87,Vendor_Master!A:A,Vendor_Master!C:C) -> 15 | M87: =INDEX(Vendor_Master!$C:$C,MATCH(B87,Vendor_Master!$A:$A,0)) -> 15 | N87: =IF(H87>Assumptions!$B$4,"Large","") -> Large | O87: =INDEX(Vendor_Master!$B:$B,MATCH(B87,Vendor_Master!$A:$A,0)) -> Housekeeping | P87: =MONTH(D87) -> 6
A88: INV-1087 | B88: Clean & Clear Housekeeping | C88: Retail Plaza | D88: 2026-06-29 | E88: 2026-07-14 | F88: 91343.05 | G88: 16441.75 | H88: 107784.8 | I88: Pending | K88: =VLOOKUP(B88,Vendor_Master!$A:$C,3,FALSE()) -> 15 | L88: =_xlfn.XLOOKUP(B88,Vendor_Master!A:A,Vendor_Master!C:C) -> 15 | M88: =INDEX(Vendor_Master!$C:$C,MATCH(B88,Vendor_Master!$A:$A,0)) -> 15 | N88: =IF(H88>Assumptions!$B$4,"Large","") -> Large | O88: =INDEX(Vendor_Master!$B:$B,MATCH(B88,Vendor_Master!$A:$A,0)) -> Housekeeping | P88: =MONTH(D88) -> 6
A89: INV-1088 | B89: GreenScape Landscaping | C89: Tower B | D89: 2026-06-30 | E89: 2026-07-30 | F89: 18558.2 | G89: 3340.48 | H89: 21898.68 | I89: Paid | J89: 2026-07-28 | K89: =VLOOKUP(B89,Vendor_Master!$A:$C,3,FALSE()) -> 30 | L89: =_xlfn.XLOOKUP(B89,Vendor_Master!A:A,Vendor_Master!C:C) -> 30 | M89: =INDEX(Vendor_Master!$C:$C,MATCH(B89,Vendor_Master!$A:$A,0)) -> 30 | N89: =IF(H89>Assumptions!$B$4,"Large","") | O89: =INDEX(Vendor_Master!$B:$B,MATCH(B89,Vendor_Master!$A:$A,0)) -> Landscaping | P89: =MONTH(D89) -> 6
A90: INV-1089 | B90: Nexus Professional Consultants | C90: Retail Plaza | D90: 2026-06-23 | E90: 2026-08-07 | F90: 35604.92 | G90: 6408.89 | H90: 42013.81 | I90: Paid | J90: 2026-08-03 | K90: =VLOOKUP(B90,Vendor_Master!$A:$C,3,FALSE()) -> 45 | L90: =_xlfn.XLOOKUP(B90,Vendor_Master!A:A,Vendor_Master!C:C) -> 45 | M90: =INDEX(Vendor_Master!$C:$C,MATCH(B90,Vendor_Master!$A:$A,0)) -> 45 | N90: =IF(H90>Assumptions!$B$4,"Large","") | O90: =INDEX(Vendor_Master!$B:$B,MATCH(B90,Vendor_Master!$A:$A,0)) -> Professional Fees | P90: =MONTH(D90) -> 6
A91: INV-1090 | B91: Nexus Professional Consultants | C91: Retail Plaza | D91: 2026-06-17 | E91: 2026-08-01 | F91: 80259.52 | G91: 14446.71 | H91: 94706.23 | I91: Paid | J91: 2026-07-29 | K91: =VLOOKUP(B91,Vendor_Master!$A:$C,3,FALSE()) -> 45 | L91: =_xlfn.XLOOKUP(B91,Vendor_Master!A:A,Vendor_Master!C:C) -> 45 | M91: =INDEX(Vendor_Master!$C:$C,MATCH(B91,Vendor_Master!$A:$A,0)) -> 45 | N91: =IF(H91>Assumptions!$B$4,"Large","") -> Large | O91: =INDEX(Vendor_Master!$B:$B,MATCH(B91,Vendor_Master!$A:$A,0)) -> Professional Fees | P91: =MONTH(D91) -> 6
A92: INV-1091 | B92: BrightWay Office Supplies | C92: Tower B | D92: 2026-06-18 | E92: 2026-07-03 | F92: 30549.66 | G92: 5498.94 | H92: 36048.6 | I92: Paid | J92: 2026-06-21 | K92: =VLOOKUP(B92,Vendor_Master!$A:$C,3,FALSE()) -> 15 | L92: =_xlfn.XLOOKUP(B92,Vendor_Master!A:A,Vendor_Master!C:C) -> 15 | M92: =INDEX(Vendor_Master!$C:$C,MATCH(B92,Vendor_Master!$A:$A,0)) -> 15 | N92: =IF(H92>Assumptions!$B$4,"Large","") | O92: =INDEX(Vendor_Master!$B:$B,MATCH(B92,Vendor_Master!$A:$A,0)) -> Office Supplies | P92: =MONTH(D92) -> 6
A93: INV-1092 | B93: Nexus Professional Consultants | C93: Commercial Block | D93: 2026-06-19 | E93: 2026-08-03 | F93: 62527.11 | G93: 11254.88 | H93: 73781.99 | I93: Pending | K93: =VLOOKUP(B93,Vendor_Master!$A:$C,3,FALSE()) -> 45 | L93: =_xlfn.XLOOKUP(B93,Vendor_Master!A:A,Vendor_Master!C:C) -> 45 | M93: =INDEX(Vendor_Master!$C:$C,MATCH(B93,Vendor_Master!$A:$A,0)) -> 45 | N93: =IF(H93>Assumptions!$B$4,"Large","") -> Large | O93: =INDEX(Vendor_Master!$B:$B,MATCH(B93,Vendor_Master!$A:$A,0)) -> Professional Fees | P93: =MONTH(D93) -> 6
A94: INV-1093 | B94: Delhi Power Utilities Pvt Ltd | C94: Commercial Block | D94: 2026-06-25 | E94: 2026-07-10 | F94: 31639.21 | G94: 5695.06 | H94: 37334.27 | I94: Paid | J94: 2026-06-26 | K94: =VLOOKUP(B94,Vendor_Master!$A:$C,3,FALSE()) -> 15 | L94: =_xlfn.XLOOKUP(B94,Vendor_Master!A:A,Vendor_Master!C:C) -> 15 | M94: =INDEX(Vendor_Master!$C:$C,MATCH(B94,Vendor_Master!$A:$A,0)) -> 15 | N94: =IF(H94>Assumptions!$B$4,"Large","") | O94: =INDEX(Vendor_Master!$B:$B,MATCH(B94,Vendor_Master!$A:$A,0)) -> Utilities | P94: =MONTH(D94) -> 6
A95: INV-1094 | B95: Clean & Clear Housekeeping | C95: Tower B | D95: 2026-06-22 | E95: 2026-07-07 | F95: 28119.75 | G95: 5061.55 | H95: 33181.3 | I95: Paid | J95: 2026-06-23 | K95: =VLOOKUP(B95,Vendor_Master!$A:$C,3,FALSE()) -> 15 | L95: =_xlfn.XLOOKUP(B95,Vendor_Master!A:A,Vendor_Master!C:C) -> 15 | M95: =INDEX(Vendor_Master!$C:$C,MATCH(B95,Vendor_Master!$A:$A,0)) -> 15 | N95: =IF(H95>Assumptions!$B$4,"Large","") | O95: =INDEX(Vendor_Master!$B:$B,MATCH(B95,Vendor_Master!$A:$A,0)) -> Housekeeping | P95: =MONTH(D95) -> 6
A96: INV-1095 | B96: Capital Insurance Brokers | C96: Retail Plaza | D96: 2026-06-30 | E96: 2026-08-14 | F96: 36786.68 | G96: 6621.6 | H96: 43408.28 | I96: Pending | K96: =VLOOKUP(B96,Vendor_Master!$A:$C,3,FALSE()) -> 45 | L96: =_xlfn.XLOOKUP(B96,Vendor_Master!A:A,Vendor_Master!C:C) -> 45 | M96: =INDEX(Vendor_Master!$C:$C,MATCH(B96,Vendor_Master!$A:$A,0)) -> 45 | N96: =IF(H96>Assumptions!$B$4,"Large","") | O96: =INDEX(Vendor_Master!$B:$B,MATCH(B96,Vendor_Master!$A:$A,0)) -> Insurance | P96: =MONTH(D96) -> 6
A97: INV-1096 | B97: GreenScape Landscaping | C97: Tower A | D97: 2026-06-30 | E97: 2026-07-30 | F97: 44552.49 | G97: 8019.45 | H97: 52571.94 | I97: Paid | J97: 2026-07-19 | K97: =VLOOKUP(B97,Vendor_Master!$A:$C,3,FALSE()) -> 30 | L97: =_xlfn.XLOOKUP(B97,Vendor_Master!A:A,Vendor_Master!C:C) -> 30 | M97: =INDEX(Vendor_Master!$C:$C,MATCH(B97,Vendor_Master!$A:$A,0)) -> 30 | N97: =IF(H97>Assumptions!$B$4,"Large","") | O97: =INDEX(Vendor_Master!$B:$B,MATCH(B97,Vendor_Master!$A:$A,0)) -> Landscaping | P97: =MONTH(D97) -> 6
A98: INV-1097 | B98: BrightWay Office Supplies | C98: Commercial Block | D98: 2026-06-18 | E98: 2026-07-03 | F98: 90018.52 | G98: 16203.33 | H98: 106221.85 | I98: Paid | J98: 2026-06-26 | K98: =VLOOKUP(B98,Vendor_Master!$A:$C,3,FALSE()) -> 15 | L98: =_xlfn.XLOOKUP(B98,Vendor_Master!A:A,Vendor_Master!C:C) -> 15 | M98: =INDEX(Vendor_Master!$C:$C,MATCH(B98,Vendor_Master!$A:$A,0)) -> 15 | N98: =IF(H98>Assumptions!$B$4,"Large","") -> Large | O98: =INDEX(Vendor_Master!$B:$B,MATCH(B98,Vendor_Master!$A:$A,0)) -> Office Supplies | P98: =MONTH(D98) -> 6
A99: INV-1098 | B99: Nexus Professional Consultants | C99: Tower B | D99: 2026-06-30 | E99: 2026-08-14 | F99: 71913.16 | G99: 12944.37 | H99: 84857.53 | I99: Pending | K99: =VLOOKUP(B99,Vendor_Master!$A:$C,3,FALSE()) -> 45 | L99: =_xlfn.XLOOKUP(B99,Vendor_Master!A:A,Vendor_Master!C:C) -> 45 | M99: =INDEX(Vendor_Master!$C:$C,MATCH(B99,Vendor_Master!$A:$A,0)) -> 45 | N99: =IF(H99>Assumptions!$B$4,"Large","") -> Large | O99: =INDEX(Vendor_Master!$B:$B,MATCH(B99,Vendor_Master!$A:$A,0)) -> Professional Fees | P99: =MONTH(D99) -> 6
A100: INV-1099 | B100: Delhi Power Utilities Pvt Ltd | C100: Retail Plaza | D100: 2026-06-30 | E100: 2026-07-15 | F100: 50250.85 | G100: 9045.15 | H100: 59296 | I100: Pending | K100: =VLOOKUP(B100,Vendor_Master!$A:$C,3,FALSE()) -> 15 | L100: =_xlfn.XLOOKUP(B100,Vendor_Master!A:A,Vendor_Master!C:C) -> 15 | M100: =INDEX(Vendor_Master!$C:$C,MATCH(B100,Vendor_Master!$A:$A,0)) -> 15 | N100: =IF(H100>Assumptions!$B$4,"Large","") | O100: =INDEX(Vendor_Master!$B:$B,MATCH(B100,Vendor_Master!$A:$A,0)) -> Utilities | P100: =MONTH(D100) -> 6
...

Sheet PivotTable_Analysis
A3: Sum of Total_Amount | B3: Payment_Status
A4: Category_Lookup | B4: Overdue | C4: Paid | D4: Pending | E4: Total Result
A5: Housekeeping | B5: 176514.52 | C5: 383814.6 | D5: 107784.8 | E5: 668113.92
A6: Insurance | B6: 69289.95 | C6: 192487.37 | D6: 127640.72 | E6: 389418.04
A7: Landscaping | B7: 11947.51 | C7: 458479.15 | D7: 90106 | E7: 560532.66
A8: Maintenance | B8: 202823.68 | C8: 927746 | D8: 29400.73 | E8: 1159970.4
A9: Marketing | B9: 18233.18 | C9: 119719.48 | D9: 128668.63 | E9: 266621.29
A10: Office Supplies | B10: 31378.58 | C10: 226557.38 | E10: 257935.96
A11: Professional Fees | B11: 111661.83 | C11: 652777.28 | D11: 158639.52 | E11: 923078.63
A12: Repairs | B12: 61735.58 | C12: 504788.32 | E12: 566523.9
A13: Security | B13: 93918.83 | C13: 390893.44 | D13: 53441.39 | E13: 538253.66
A14: Utilities | B14: 31985.69 | C14: 488193.49 | D14: 102342.02 | E14: 622521.2
A15: Total Result | B15: 809489.35 | C15: 4345456.5 | D15: 798023.81 | E15: 5952969.7

Sheet Summary
A1: Monthly Spend by Category (Total_Amount)
A2: Category | B2: Jan | C2: Feb | D2: Mar | E2: Apr | F2: May | G2: Jun
A3: Housekeeping | B3: =SUMIFS(Raw_Data!$H$2:$H$104,Raw_Data!$O$2:$O$104,$A3,Raw_Data!$P$2:$P$104,1) -> 0 | C3: =SUMIFS(Raw_Data!$H$2:$H$104,Raw_Data!$O$2:$O$104,$A3,Raw_Data!$P$2:$P$104,2) -> 176514.52 | D3: =SUMIFS(Raw_Data!$H$2:$H$104,Raw_Data!$O$2:$O$104,$A3,Raw_Data!$P$2:$P$104,3) -> 70526.3 | E3: =SUMIFS(Raw_Data!$H$2:$H$104,Raw_Data!$O$2:$O$104,$A3,Raw_Data!$P$2:$P$104,4) -> 0 | F3: =SUMIFS(Raw_Data!$H$2:$H$104,Raw_Data!$O$2:$O$104,$A3,Raw_Data!$P$2:$P$104,5) -> 200075.68 | G3: =SUMIFS(Raw_Data!$H$2:$H$104,Raw_Data!$O$2:$O$104,$A3,Raw_Data!$P$2:$P$104,6) -> 220997.42
A4: Insurance | B4: =SUMIFS(Raw_Data!$H$2:$H$104,Raw_Data!$O$2:$O$104,$A4,Raw_Data!$P$2:$P$104,1) -> 55555.8 | C4: =SUMIFS(Raw_Data!$H$2:$H$104,Raw_Data!$O$2:$O$104,$A4,Raw_Data!$P$2:$P$104,2) -> 72507.48 | D4: =SUMIFS(Raw_Data!$H$2:$H$104,Raw_Data!$O$2:$O$104,$A4,Raw_Data!$P$2:$P$104,3) -> 19123.48 | E4: =SUMIFS(Raw_Data!$H$2:$H$104,Raw_Data!$O$2:$O$104,$A4,Raw_Data!$P$2:$P$104,4) -> 13734.15 | F4: =SUMIFS(Raw_Data!$H$2:$H$104,Raw_Data!$O$2:$O$104,$A4,Raw_Data!$P$2:$P$104,5) -> 185088.85 | G4: =SUMIFS(Raw_Data!$H$2:$H$104,Raw_Data!$O$2:$O$104,$A4,Raw_Data!$P$2:$P$104,6) -> 43408.28
A5: Landscaping | B5: =SUMIFS(Raw_Data!$H$2:$H$104,Raw_Data!$O$2:$O$104,$A5,Raw_Data!$P$2:$P$104,1) -> 43994.8 | C5: =SUMIFS(Raw_Data!$H$2:$H$104,Raw_Data!$O$2:$O$104,$A5,Raw_Data!$P$2:$P$104,2) -> 99407.9 | D5: =SUMIFS(Raw_Data!$H$2:$H$104,Raw_Data!$O$2:$O$104,$A5,Raw_Data!$P$2:$P$104,3) -> 120061.11 | E5: =SUMIFS(Raw_Data!$H$2:$H$104,Raw_Data!$O$2:$O$104,$A5,Raw_Data!$P$2:$P$104,4) -> 120544.72 | F5: =SUMIFS(Raw_Data!$H$2:$H$104,Raw_Data!$O$2:$O$104,$A5,Raw_Data!$P$2:$P$104,5) -> 11947.51 | G5: =SUMIFS(Raw_Data!$H$2:$H$104,Raw_Data!$O$2:$O$104,$A5,Raw_Data!$P$2:$P$104,6) -> 164576.62
A6: Maintenance | B6: =SUMIFS(Raw_Data!$H$2:$H$104,Raw_Data!$O$2:$O$104,$A6,Raw_Data!$P$2:$P$104,1) -> 489180.26 | C6: =SUMIFS(Raw_Data!$H$2:$H$104,Raw_Data!$O$2:$O$104,$A6,Raw_Data!$P$2:$P$104,2) -> 107221.69 | D6: =SUMIFS(Raw_Data!$H$2:$H$104,Raw_Data!$O$2:$O$104,$A6,Raw_Data!$P$2:$P$104,3) -> 154507.83 | E6: =SUMIFS(Raw_Data!$H$2:$H$104,Raw_Data!$O$2:$O$104,$A6,Raw_Data!$P$2:$P$104,4) -> 166532.12 | F6: =SUMIFS(Raw_Data!$H$2:$H$104,Raw_Data!$O$2:$O$104,$A6,Raw_Data!$P$2:$P$104,5) -> 104419.59 | G6: =SUMIFS(Raw_Data!$H$2:$H$104,Raw_Data!$O$2:$O$104,$A6,Raw_Data!$P$2:$P$104,6) -> 138108.92
A7: Marketing | B7: =SUMIFS(Raw_Data!$H$2:$H$104,Raw_Data!$O$2:$O$104,$A7,Raw_Data!$P$2:$P$104,1) -> 46565.45 | C7: =SUMIFS(Raw_Data!$H$2:$H$104,Raw_Data!$O$2:$O$104,$A7,Raw_Data!$P$2:$P$104,2) -> 18233.18 | D7: =SUMIFS(Raw_Data!$H$2:$H$104,Raw_Data!$O$2:$O$104,$A7,Raw_Data!$P$2:$P$104,3) -> 0 | E7: =SUMIFS(Raw_Data!$H$2:$H$104,Raw_Data!$O$2:$O$104,$A7,Raw_Data!$P$2:$P$104,4) -> 41918.53 | F7: =SUMIFS(Raw_Data!$H$2:$H$104,Raw_Data!$O$2:$O$104,$A7,Raw_Data!$P$2:$P$104,5) -> 19027.13 | G7: =SUMIFS(Raw_Data!$H$2:$H$104,Raw_Data!$O$2:$O$104,$A7,Raw_Data!$P$2:$P$104,6) -> 140877
A8: Office Supplies | B8: =SUMIFS(Raw_Data!$H$2:$H$104,Raw_Data!$O$2:$O$104,$A8,Raw_Data!$P$2:$P$104,1) -> 0 | C8: =SUMIFS(Raw_Data!$H$2:$H$104,Raw_Data!$O$2:$O$104,$A8,Raw_Data!$P$2:$P$104,2) -> 0 | D8: =SUMIFS(Raw_Data!$H$2:$H$104,Raw_Data!$O$2:$O$104,$A8,Raw_Data!$P$2:$P$104,3) -> 84286.93 | E8: =SUMIFS(Raw_Data!$H$2:$H$104,Raw_Data!$O$2:$O$104,$A8,Raw_Data!$P$2:$P$104,4) -> 0 | F8: =SUMIFS(Raw_Data!$H$2:$H$104,Raw_Data!$O$2:$O$104,$A8,Raw_Data!$P$2:$P$104,5) -> 0 | G8: =SUMIFS(Raw_Data!$H$2:$H$104,Raw_Data!$O$2:$O$104,$A8,Raw_Data!$P$2:$P$104,6) -> 173649.03
A9: Professional Fees | B9: =SUMIFS(Raw_Data!$H$2:$H$104,Raw_Data!$O$2:$O$104,$A9,Raw_Data!$P$2:$P$104,1) -> 0 | C9: =SUMIFS(Raw_Data!$H$2:$H$104,Raw_Data!$O$2:$O$104,$A9,Raw_Data!$P$2:$P$104,2) -> 314113.56 | D9: =SUMIFS(Raw_Data!$H$2:$H$104,Raw_Data!$O$2:$O$104,$A9,Raw_Data!$P$2:$P$104,3) -> 190424.66 | E9: =SUMIFS(Raw_Data!$H$2:$H$104,Raw_Data!$O$2:$O$104,$A9,Raw_Data!$P$2:$P$104,4) -> 23037.99 | F9: =SUMIFS(Raw_Data!$H$2:$H$104,Raw_Data!$O$2:$O$104,$A9,Raw_Data!$P$2:$P$104,5) -> 100142.86 | G9: =SUMIFS(Raw_Data!$H$2:$H$104,Raw_Data!$O$2:$O$104,$A9,Raw_Data!$P$2:$P$104,6) -> 295359.56
A10: Repairs | B10: =SUMIFS(Raw_Data!$H$2:$H$104,Raw_Data!$O$2:$O$104,$A10,Raw_Data!$P$2:$P$104,1) -> 36595.72 | C10: =SUMIFS(Raw_Data!$H$2:$H$104,Raw_Data!$O$2:$O$104,$A10,Raw_Data!$P$2:$P$104,2) -> 243884.49 | D10: =SUMIFS(Raw_Data!$H$2:$H$104,Raw_Data!$O$2:$O$104,$A10,Raw_Data!$P$2:$P$104,3) -> 0 | E10: =SUMIFS(Raw_Data!$H$2:$H$104,Raw_Data!$O$2:$O$104,$A10,Raw_Data!$P$2:$P$104,4) -> 25634.28 | F10: =SUMIFS(Raw_Data!$H$2:$H$104,Raw_Data!$O$2:$O$104,$A10,Raw_Data!$P$2:$P$104,5) -> 260409.41 | G10: =SUMIFS(Raw_Data!$H$2:$H$104,Raw_Data!$O$2:$O$104,$A10,Raw_Data!$P$2:$P$104,6) -> 0
A11: Security | B11: =SUMIFS(Raw_Data!$H$2:$H$104,Raw_Data!$O$2:$O$104,$A11,Raw_Data!$P$2:$P$104,1) -> 141073.97 | C11: =SUMIFS(Raw_Data!$H$2:$H$104,Raw_Data!$O$2:$O$104,$A11,Raw_Data!$P$2:$P$104,2) -> 99649.58 | D11: =SUMIFS(Raw_Data!$H$2:$H$104,Raw_Data!$O$2:$O$104,$A11,Raw_Data!$P$2:$P$104,3) -> 179726.87 | E11: =SUMIFS(Raw_Data!$H$2:$H$104,Raw_Data!$O$2:$O$104,$A11,Raw_Data!$P$2:$P$104,4) -> 36590.08 | F11: =SUMIFS(Raw_Data!$H$2:$H$104,Raw_Data!$O$2:$O$104,$A11,Raw_Data!$P$2:$P$104,5) -> 27771.77 | G11: =SUMIFS(Raw_Data!$H$2:$H$104,Raw_Data!$O$2:$O$104,$A11,Raw_Data!$P$2:$P$104,6) -> 53441.39
A12: Utilities | B12: =SUMIFS(Raw_Data!$H$2:$H$104,Raw_Data!$O$2:$O$104,$A12,Raw_Data!$P$2:$P$104,1) -> 0 | C12: =SUMIFS(Raw_Data!$H$2:$H$104,Raw_Data!$O$2:$O$104,$A12,Raw_Data!$P$2:$P$104,2) -> 31985.69 | D12: =SUMIFS(Raw_Data!$H$2:$H$104,Raw_Data!$O$2:$O$104,$A12,Raw_Data!$P$2:$P$104,3) -> 116037.21 | E12: =SUMIFS(Raw_Data!$H$2:$H$104,Raw_Data!$O$2:$O$104,$A12,Raw_Data!$P$2:$P$104,4) -> 206378.79 | F12: =SUMIFS(Raw_Data!$H$2:$H$104,Raw_Data!$O$2:$O$104,$A12,Raw_Data!$P$2:$P$104,5) -> 77077.61 | G12: =SUMIFS(Raw_Data!$H$2:$H$104,Raw_Data!$O$2:$O$104,$A12,Raw_Data!$P$2:$P$104,6) -> 191041.9
A13: Total | B13: =SUM(B3:B12) -> 812966 | C13: =SUM(C3:C12) -> 1163518.1 | D13: =SUM(D3:D12) -> 934694.39 | E13: =SUM(E3:E12) -> 634370.66 | F13: =SUM(F3:F12) -> 985960.41 | G13: =SUM(G3:G12) -> 1421460.1
A20: Total Spend by Category (overall)
A21: Category | B21: Total_Amount
A22: Housekeeping | B22: =SUMIFS(Raw_Data!$H$2:$H$104,Raw_Data!$O$2:$O$104,$A22) -> 668113.92
A23: Insurance | B23: =SUMIFS(Raw_Data!$H$2:$H$104,Raw_Data!$O$2:$O$104,$A23) -> 389418.04
A24: Landscaping | B24: =SUMIFS(Raw_Data!$H$2:$H$104,Raw_Data!$O$2:$O$104,$A24) -> 560532.66
A25: Maintenance | B25: =SUMIFS(Raw_Data!$H$2:$H$104,Raw_Data!$O$2:$O$104,$A25) -> 1159970.4
A26: Marketing | B26: =SUMIFS(Raw_Data!$H$2:$H$104,Raw_Data!$O$2:$O$104,$A26) -> 266621.29
A27: Office Supplies | B27: =SUMIFS(Raw_Data!$H$2:$H$104,Raw_Data!$O$2:$O$104,$A27) -> 257935.96
A28: Professional Fees | B28: =SUMIFS(Raw_Data!$H$2:$H$104,Raw_Data!$O$2:$O$104,$A28) -> 923078.63
A29: Repairs | B29: =SUMIFS(Raw_Data!$H$2:$H$104,Raw_Data!$O$2:$O$104,$A29) -> 566523.9
A30: Security | B30: =SUMIFS(Raw_Data!$H$2:$H$104,Raw_Data!$O$2:$O$104,$A30) -> 538253.66
A31: Utilities | B31: =SUMIFS(Raw_Data!$H$2:$H$104,Raw_Data!$O$2:$O$104,$A31) -> 622521.2
A35: Filtered Breakdown (auto-updates with Dashboard month selector)
A36: Category | B36: Total_Amount
A37: Housekeeping | B37: =IF(Dashboard!$B$4="All",$B$22,INDEX($B$3:$G$3,1,MATCH(Dashboard!$B$4,{"Jan","Feb","Mar","Apr","May","Jun"},0))) -> 668113.92
A38: Insurance | B38: =IF(Dashboard!$B$4="All",$B$23,INDEX($B$4:$G$4,1,MATCH(Dashboard!$B$4,{"Jan","Feb","Mar","Apr","May","Jun"},0))) -> 389418.04
A39: Landscaping | B39: =IF(Dashboard!$B$4="All",$B$24,INDEX($B$5:$G$5,1,MATCH(Dashboard!$B$4,{"Jan","Feb","Mar","Apr","May","Jun"},0))) -> 560532.66
A40: Maintenance | B40: =IF(Dashboard!$B$4="All",$B$25,INDEX($B$6:$G$6,1,MATCH(Dashboard!$B$4,{"Jan","Feb","Mar","Apr","May","Jun"},0))) -> 1159970.4
A41: Marketing | B41: =IF(Dashboard!$B$4="All",$B$26,INDEX($B$7:$G$7,1,MATCH(Dashboard!$B$4,{"Jan","Feb","Mar","Apr","May","Jun"},0))) -> 266621.29
A42: Office Supplies | B42: =IF(Dashboard!$B$4="All",$B$27,INDEX($B$8:$G$8,1,MATCH(Dashboard!$B$4,{"Jan","Feb","Mar","Apr","May","Jun"},0))) -> 257935.96
A43: Professional Fees | B43: =IF(Dashboard!$B$4="All",$B$28,INDEX($B$9:$G$9,1,MATCH(Dashboard!$B$4,{"Jan","Feb","Mar","Apr","May","Jun"},0))) -> 923078.63
A44: Repairs | B44: =IF(Dashboard!$B$4="All",$B$29,INDEX($B$10:$G$10,1,MATCH(Dashboard!$B$4,{"Jan","Feb","Mar","Apr","May","Jun"},0))) -> 566523.9
A45: Security | B45: =IF(Dashboard!$B$4="All",$B$30,INDEX($B$11:$G$11,1,MATCH(Dashboard!$B$4,{"Jan","Feb","Mar","Apr","May","Jun"},0))) -> 538253.66
A46: Utilities | B46: =IF(Dashboard!$B$4="All",$B$31,INDEX($B$12:$G$12,1,MATCH(Dashboard!$B$4,{"Jan","Feb","Mar","Apr","May","Jun"},0))) -> 622521.2
A60: Live Pivot — Category x Payment Status (auto-updates with month selector)
A61: Category | B61: Paid | C61: Pending | D61: Overdue | E61: Grand Total
A62: Housekeeping | B62: =IF(Dashboard!$B$4="All",SUMIFS(Raw_Data!$H$2:$H$104,Raw_Data!$O$2:$O$104,$A62,Raw_Data!$I$2:$I$104,"Paid"),SUMIFS(Raw_Data!$H$2:$H$104,Raw_Data!$O$2:$O$104,$A62,Raw_Data!$I$2:$I$104,"Paid",Raw_Data!$P$2:$P$104,MATCH(Dashboard!$B$4,{"Jan","Feb","Mar","Apr","May","Jun"},0))) -> 383814.6 | C62: =IF(Dashboard!$B$4="All",SUMIFS(Raw_Data!$H$2:$H$104,Raw_Data!$O$2:$O$104,$A62,Raw_Data!$I$2:$I$104,"Pending"),SUMIFS(Raw_Data!$H$2:$H$104,Raw_Data!$O$2:$O$104,$A62,Raw_Data!$I$2:$I$104,"Pending",Raw_Data!$P$2:$P$104,MATCH(Dashboard!$B$4,{"Jan","Feb","Mar","Apr","May","Jun"},0))) -> 107784.8 | D62: =IF(Dashboard!$B$4="All",SUMIFS(Raw_Data!$H$2:$H$104,Raw_Data!$O$2:$O$104,$A62,Raw_Data!$I$2:$I$104,"Overdue"),SUMIFS(Raw_Data!$H$2:$H$104,Raw_Data!$O$2:$O$104,$A62,Raw_Data!$I$2:$I$104,"Overdue",Raw_Data!$P$2:$P$104,MATCH(Dashboard!$B$4,{"Jan","Feb","Mar","Apr","May","Jun"},0))) -> 176514.52 | E62: =SUM(B62:D62) -> 668113.92
A63: Insurance | B63: =IF(Dashboard!$B$4="All",SUMIFS(Raw_Data!$H$2:$H$104,Raw_Data!$O$2:$O$104,$A63,Raw_Data!$I$2:$I$104,"Paid"),SUMIFS(Raw_Data!$H$2:$H$104,Raw_Data!$O$2:$O$104,$A63,Raw_Data!$I$2:$I$104,"Paid",Raw_Data!$P$2:$P$104,MATCH(Dashboard!$B$4,{"Jan","Feb","Mar","Apr","May","Jun"},0))) -> 192487.37 | C63: =IF(Dashboard!$B$4="All",SUMIFS(Raw_Data!$H$2:$H$104,Raw_Data!$O$2:$O$104,$A63,Raw_Data!$I$2:$I$104,"Pending"),SUMIFS(Raw_Data!$H$2:$H$104,Raw_Data!$O$2:$O$104,$A63,Raw_Data!$I$2:$I$104,"Pending",Raw_Data!$P$2:$P$104,MATCH(Dashboard!$B$4,{"Jan","Feb","Mar","Apr","May","Jun"},0))) -> 127640.72 | D63: =IF(Dashboard!$B$4="All",SUMIFS(Raw_Data!$H$2:$H$104,Raw_Data!$O$2:$O$104,$A63,Raw_Data!$I$2:$I$104,"Overdue"),SUMIFS(Raw_Data!$H$2:$H$104,Raw_Data!$O$2:$O$104,$A63,Raw_Data!$I$2:$I$104,"Overdue",Raw_Data!$P$2:$P$104,MATCH(Dashboard!$B$4,{"Jan","Feb","Mar","Apr","May","Jun"},0))) -> 69289.95 | E63: =SUM(B63:D63) -> 389418.04
A64: Landscaping | B64: =IF(Dashboard!$B$4="All",SUMIFS(Raw_Data!$H$2:$H$104,Raw_Data!$O$2:$O$104,$A64,Raw_Data!$I$2:$I$104,"Paid"),SUMIFS(Raw_Data!$H$2:$H$104,Raw_Data!$O$2:$O$104,$A64,Raw_Data!$I$2:$I$104,"Paid",Raw_Data!$P$2:$P$104,MATCH(Dashboard!$B$4,{"Jan","Feb","Mar","Apr","May","Jun"},0))) -> 458479.15 | C64: =IF(Dashboard!$B$4="All",SUMIFS(Raw_Data!$H$2:$H$104,Raw_Data!$O$2:$O$104,$A64,Raw_Data!$I$2:$I$104,"Pending"),SUMIFS(Raw_Data!$H$2:$H$104,Raw_Data!$O$2:$O$104,$A64,Raw_Data!$I$2:$I$104,"Pending",Raw_Data!$P$2:$P$104,MATCH(Dashboard!$B$4,{"Jan","Feb","Mar","Apr","May","Jun"},0))) -> 90106 | D64: =IF(Dashboard!$B$4="All",SUMIFS(Raw_Data!$H$2:$H$104,Raw_Data!$O$2:$O$104,$A64,Raw_Data!$I$2:$I$104,"Overdue"),SUMIFS(Raw_Data!$H$2:$H$104,Raw_Data!$O$2:$O$104,$A64,Raw_Data!$I$2:$I$104,"Overdue",Raw_Data!$P$2:$P$104,MATCH(Dashboard!$B$4,{"Jan","Feb","Mar","Apr","May","Jun"},0))) -> 11947.51 | E64: =SUM(B64:D64) -> 560532.66
A65: Maintenance | B65: =IF(Dashboard!$B$4="All",SUMIFS(Raw_Data!$H$2:$H$104,Raw_Data!$O$2:$O$104,$A65,Raw_Data!$I$2:$I$104,"Paid"),SUMIFS(Raw_Data!$H$2:$H$104,Raw_Data!$O$2:$O$104,$A65,Raw_Data!$I$2:$I$104,"Paid",Raw_Data!$P$2:$P$104,MATCH(Dashboard!$B$4,{"Jan","Feb","Mar","Apr","May","Jun"},0))) -> 927746 | C65: =IF(Dashboard!$B$4="All",SUMIFS(Raw_Data!$H$2:$H$104,Raw_Data!$O$2:$O$104,$A65,Raw_Data!$I$2:$I$104,"Pending"),SUMIFS(Raw_Data!$H$2:$H$104,Raw_Data!$O$2:$O$104,$A65,Raw_Data!$I$2:$I$104,"Pending",Raw_Data!$P$2:$P$104,MATCH(Dashboard!$B$4,{"Jan","Feb","Mar","Apr","May","Jun"},0))) -> 29400.73 | D65: =IF(Dashboard!$B$4="All",SUMIFS(Raw_Data!$H$2:$H$104,Raw_Data!$O$2:$O$104,$A65,Raw_Data!$I$2:$I$104,"Overdue"),SUMIFS(Raw_Data!$H$2:$H$104,Raw_Data!$O$2:$O$104,$A65,Raw_Data!$I$2:$I$104,"Overdue",Raw_Data!$P$2:$P$104,MATCH(Dashboard!$B$4,{"Jan","Feb","Mar","Apr","May","Jun"},0))) -> 202823.68 | E65: =SUM(B65:D65) -> 1159970.4
A66: Marketing | B66: =IF(Dashboard!$B$4="All",SUMIFS(Raw_Data!$H$2:$H$104,Raw_Data!$O$2:$O$104,$A66,Raw_Data!$I$2:$I$104,"Paid"),SUMIFS(Raw_Data!$H$2:$H$104,Raw_Data!$O$2:$O$104,$A66,Raw_Data!$I$2:$I$104,"Paid",Raw_Data!$P$2:$P$104,MATCH(Dashboard!$B$4,{"Jan","Feb","Mar","Apr","May","Jun"},0))) -> 119719.48 | C66: =IF(Dashboard!$B$4="All",SUMIFS(Raw_Data!$H$2:$H$104,Raw_Data!$O$2:$O$104,$A66,Raw_Data!$I$2:$I$104,"Pending"),SUMIFS(Raw_Data!$H$2:$H$104,Raw_Data!$O$2:$O$104,$A66,Raw_Data!$I$2:$I$104,"Pending",Raw_Data!$P$2:$P$104,MATCH(Dashboard!$B$4,{"Jan","Feb","Mar","Apr","May","Jun"},0))) -> 128668.63 | D66: =IF(Dashboard!$B$4="All",SUMIFS(Raw_Data!$H$2:$H$104,Raw_Data!$O$2:$O$104,$A66,Raw_Data!$I$2:$I$104,"Overdue"),SUMIFS(Raw_Data!$H$2:$H$104,Raw_Data!$O$2:$O$104,$A66,Raw_Data!$I$2:$I$104,"Overdue",Raw_Data!$P$2:$P$104,MATCH(Dashboard!$B$4,{"Jan","Feb","Mar","Apr","May","Jun"},0))) -> 18233.18 | E66: =SUM(B66:D66) -> 266621.29
A67: Office Supplies | B67: =IF(Dashboard!$B$4="All",SUMIFS(Raw_Data!$H$2:$H$104,Raw_Data!$O$2:$O$104,$A67,Raw_Data!$I$2:$I$104,"Paid"),SUMIFS(Raw_Data!$H$2:$H$104,Raw_Data!$O$2:$O$104,$A67,Raw_Data!$I$2:$I$104,"Paid",Raw_Data!$P$2:$P$104,MATCH(Dashboard!$B$4,{"Jan","Feb","Mar","Apr","May","Jun"},0))) -> 226557.38 | C67: =IF(Dashboard!$B$4="All",SUMIFS(Raw_Data!$H$2:$H$104,Raw_Data!$O$2:$O$104,$A67,Raw_Data!$I$2:$I$104,"Pending"),SUMIFS(Raw_Data!$H$2:$H$104,Raw_Data!$O$2:$O$104,$A67,Raw_Data!$I$2:$I$104,"Pending",Raw_Data!$P$2:$P$104,MATCH(Dashboard!$B$4,{"Jan","Feb","Mar","Apr","May","Jun"},0))) -> 0 | D67: =IF(Dashboard!$B$4="All",SUMIFS(Raw_Data!$H$2:$H$104,Raw_Data!$O$2:$O$104,$A67,Raw_Data!$I$2:$I$104,"Overdue"),SUMIFS(Raw_Data!$H$2:$H$104,Raw_Data!$O$2:$O$104,$A67,Raw_Data!$I$2:$I$104,"Overdue",Raw_Data!$P$2:$P$104,MATCH(Dashboard!$B$4,{"Jan","Feb","Mar","Apr","May","Jun"},0))) -> 31378.58 | E67: =SUM(B67:D67) -> 257935.96
A68: Professional Fees | B68: =IF(Dashboard!$B$4="All",SUMIFS(Raw_Data!$H$2:$H$104,Raw_Data!$O$2:$O$104,$A68,Raw_Data!$I$2:$I$104,"Paid"),SUMIFS(Raw_Data!$H$2:$H$104,Raw_Data!$O$2:$O$104,$A68,Raw_Data!$I$2:$I$104,"Paid",Raw_Data!$P$2:$P$104,MATCH(Dashboard!$B$4,{"Jan","Feb","Mar","Apr","May","Jun"},0))) -> 652777.28 | C68: =IF(Dashboard!$B$4="All",SUMIFS(Raw_Data!$H$2:$H$104,Raw_Data!$O$2:$O$104,$A68,Raw_Data!$I$2:$I$104,"Pending"),SUMIFS(Raw_Data!$H$2:$H$104,Raw_Data!$O$2:$O$104,$A68,Raw_Data!$I$2:$I$104,"Pending",Raw_Data!$P$2:$P$104,MATCH(Dashboard!$B$4,{"Jan","Feb","Mar","Apr","May","Jun"},0))) -> 158639.52 | D68: =IF(Dashboard!$B$4="All",SUMIFS(Raw_Data!$H$2:$H$104,Raw_Data!$O$2:$O$104,$A68,Raw_Data!$I$2:$I$104,"Overdue"),SUMIFS(Raw_Data!$H$2:$H$104,Raw_Data!$O$2:$O$104,$A68,Raw_Data!$I$2:$I$104,"Overdue",Raw_Data!$P$2:$P$104,MATCH(Dashboard!$B$4,{"Jan","Feb","Mar","Apr","May","Jun"},0))) -> 111661.83 | E68: =SUM(B68:D68) -> 923078.63
A69: Repairs | B69: =IF(Dashboard!$B$4="All",SUMIFS(Raw_Data!$H$2:$H$104,Raw_Data!$O$2:$O$104,$A69,Raw_Data!$I$2:$I$104,"Paid"),SUMIFS(Raw_Data!$H$2:$H$104,Raw_Data!$O$2:$O$104,$A69,Raw_Data!$I$2:$I$104,"Paid",Raw_Data!$P$2:$P$104,MATCH(Dashboard!$B$4,{"Jan","Feb","Mar","Apr","May","Jun"},0))) -> 504788.32 | C69: =IF(Dashboard!$B$4="All",SUMIFS(Raw_Data!$H$2:$H$104,Raw_Data!$O$2:$O$104,$A69,Raw_Data!$I$2:$I$104,"Pending"),SUMIFS(Raw_Data!$H$2:$H$104,Raw_Data!$O$2:$O$104,$A69,Raw_Data!$I$2:$I$104,"Pending",Raw_Data!$P$2:$P$104,MATCH(Dashboard!$B$4,{"Jan","Feb","Mar","Apr","May","Jun"},0))) -> 0 | D69: =IF(Dashboard!$B$4="All",SUMIFS(Raw_Data!$H$2:$H$104,Raw_Data!$O$2:$O$104,$A69,Raw_Data!$I$2:$I$104,"Overdue"),SUMIFS(Raw_Data!$H$2:$H$104,Raw_Data!$O$2:$O$104,$A69,Raw_Data!$I$2:$I$104,"Overdue",Raw_Data!$P$2:$P$104,MATCH(Dashboard!$B$4,{"Jan","Feb","Mar","Apr","May","Jun"},0))) -> 61735.58 | E69: =SUM(B69:D69) -> 566523.9
A70: Security | B70: =IF(Dashboard!$B$4="All",SUMIFS(Raw_Data!$H$2:$H$104,Raw_Data!$O$2:$O$104,$A70,Raw_Data!$I$2:$I$104,"Paid"),SUMIFS(Raw_Data!$H$2:$H$104,Raw_Data!$O$2:$O$104,$A70,Raw_Data!$I$2:$I$104,"Paid",Raw_Data!$P$2:$P$104,MATCH(Dashboard!$B$4,{"Jan","Feb","Mar","Apr","May","Jun"},0))) -> 390893.44 | C70: =IF(Dashboard!$B$4="All",SUMIFS(Raw_Data!$H$2:$H$104,Raw_Data!$O$2:$O$104,$A70,Raw_Data!$I$2:$I$104,"Pending"),SUMIFS(Raw_Data!$H$2:$H$104,Raw_Data!$O$2:$O$104,$A70,Raw_Data!$I$2:$I$104,"Pending",Raw_Data!$P$2:$P$104,MATCH(Dashboard!$B$4,{"Jan","Feb","Mar","Apr","May","Jun"},0))) -> 53441.39 | D70: =IF(Dashboard!$B$4="All",SUMIFS(Raw_Data!$H$2:$H$104,Raw_Data!$O$2:$O$104,$A70,Raw_Data!$I$2:$I$104,"Overdue"),SUMIFS(Raw_Data!$H$2:$H$104,Raw_Data!$O$2:$O$104,$A70,Raw_Data!$I$2:$I$104,"Overdue",Raw_Data!$P$2:$P$104,MATCH(Dashboard!$B$4,{"Jan","Feb","Mar","Apr","May","Jun"},0))) -> 93918.83 | E70: =SUM(B70:D70) -> 538253.66
A71: Utilities | B71: =IF(Dashboard!$B$4="All",SUMIFS(Raw_Data!$H$2:$H$104,Raw_Data!$O$2:$O$104,$A71,Raw_Data!$I$2:$I$104,"Paid"),SUMIFS(Raw_Data!$H$2:$H$104,Raw_Data!$O$2:$O$104,$A71,Raw_Data!$I$2:$I$104,"Paid",Raw_Data!$P$2:$P$104,MATCH(Dashboard!$B$4,{"Jan","Feb","Mar","Apr","May","Jun"},0))) -> 488193.49 | C71: =IF(Dashboard!$B$4="All",SUMIFS(Raw_Data!$H$2:$H$104,Raw_Data!$O$2:$O$104,$A71,Raw_Data!$I$2:$I$104,"Pending"),SUMIFS(Raw_Data!$H$2:$H$104,Raw_Data!$O$2:$O$104,$A71,Raw_Data!$I$2:$I$104,"Pending",Raw_Data!$P$2:$P$104,MATCH(Dashboard!$B$4,{"Jan","Feb","Mar","Apr","May","Jun"},0))) -> 102342.02 | D71: =IF(Dashboard!$B$4="All",SUMIFS(Raw_Data!$H$2:$H$104,Raw_Data!$O$2:$O$104,$A71,Raw_Data!$I$2:$I$104,"Overdue"),SUMIFS(Raw_Data!$H$2:$H$104,Raw_Data!$O$2:$O$104,$A71,Raw_Data!$I$2:$I$104,"Overdue",Raw_Data!$P$2:$P$104,MATCH(Dashboard!$B$4,{"Jan","Feb","Mar","Apr","May","Jun"},0))) -> 31985.69 | E71: =SUM(B71:D71) -> 622521.2
A72: Grand Total | B72: =SUM(B62:B71) -> 4345456.5 | C72: =SUM(C62:C71) -> 798023.81 | D72: =SUM(D62:D71) -> 809489.35 | E72: =SUM(E62:E71) -> 5952969.7
