Workbook

Sheet Cover
B2: Titan Company Limited
B3: Financial Statement Analysis — FY2023 to FY2025
B4: Prepared by: Akriti Tripathi
B5: Data Source: Titan Company Limited — Standalone Audited Financial Statements
B6: Annual Reports used: FY2022-23, FY2023-24, FY2024-25 (as published on titancompany.in / BSE-NSE filings)
B7: Figures: ₹ in Crore, unless stated otherwise. Standalone financials used throughout (not consolidated).
B9: Contents
B10: 1. Income Statement Summary
B11: 2. Balance Sheet Summary
B12: 3. Cash Flow Summary
B13: 4. Ratio Analysis
B14: 5. Trend Analysis
B15: 6. Observations

Sheet Income Statement
A1: Standalone Income Statement Summary
A4: Particulars | B4: FY2023 | C4: FY2024 | D4: FY2025
A5: Revenue from Operations | B5: 38270 | C5: 47114 | D5: 54842
A6: Other Income | B6: 299 | C6: 510 | D6: 493
A7: Total Income | B7: =B5+B6 -> 38569 | C7: =C5+C6 -> 47624 | D7: =D5+D6 -> 55335
A8: Cost of Raw Materials & Components Consumed | B8: 25085 | C8: 33556 | D8: 43905
A9: Purchase of Stock-in-Trade | B9: 5438 | C9: 5535 | D9: 6372
A10: Changes in Inventories (Fin. Goods/Stock/WIP) | B10: -1477 | C10: -2149 | D10: -6537
A11: Employee Benefits Expense | B11: 1362 | C11: 1503 | D11: 1717
A12: Finance Costs | B12: 240 | C12: 480 | D12: 767
A13: Depreciation & Amortisation Expense | B13: 364 | C13: 447 | D13: 537
A14: Other Expenses | B14: 3092 | C14: 3645 | D14: 4093
A15: Total Expenses | B15: =SUM(B8:B14) -> 34104 | C15: =SUM(C8:C14) -> 43017 | D15: =SUM(D8:D14) -> 50854
A16: Profit Before Tax (PBT) | B16: =B7-B15 -> 4465 | C16: =C7-C15 -> 4607 | D16: =D7-D15 -> 4481
A17: Total Tax Expense | B17: 1132 | C17: 1063 | D17: 1146
A18: Profit for the Year (PAT) | B18: =B16-B17 -> 3333 | C18: =C16-C17 -> 3544 | D18: =D16-D17 -> 3335
A19: Basic EPS (₹) | B19: 37.54 | C19: 39.94 | D19: 37.6
A21: Revenue Growth % (YoY) | B21: - | C21: =(C5-B5)/B5 -> 0.23109485 | D21: =(D5-C5)/C5 -> 0.16402768
A22: Net Profit Growth % (YoY) | B22: - | C22: =(C18-B18)/B18 -> 0.063306331 | D22: =(D18-C18)/C18 -> -0.058972912

Sheet Balance Sheet
A1: Standalone Balance Sheet Summary
A4: Particulars | B4: FY2023 | C4: FY2024 | D4: FY2025
A5: ASSETS
A6: Non-current Assets (total) | B6: 4402 | C6: 10169 | D6: 10631
A7: Current Assets (total) | B7: 20686 | C7: 22693 | D7: 30444
A8: of which: Inventories | B8: 14952 | C8: 16874 | D8: 24517
A9: of which: Trade Receivables | B9: 908 | C9: 937 | D9: 984
A10: of which: Cash & Cash Equivalents | B10: 119 | C10: 272 | D10: 243
A11: TOTAL ASSETS | B11: =B6+B7 -> 25088 | C11: =C6+C7 -> 32862 | D11: =D6+D7 -> 41075
A13: EQUITY & LIABILITIES
A14: Equity Share Capital | B14: 89 | C14: 89 | D14: 89
A15: Other Equity | B15: 11905 | C15: 14368 | D15: 16722
A16: TOTAL EQUITY | B16: =B14+B15 -> 11994 | C16: =C14+C15 -> 14457 | D16: =D14+D15 -> 16811
A17: Non-current Liabilities (total) | B17: 1573 | C17: 5043 | D17: 2619
A18: of which: Lease Liabilities (NC) | B18: 1359 | C18: 1666 | D18: 1943
A19: of which: Borrowings (NC) | B19: 0 | C19: 3139 | D19: 420
A20: Current Liabilities (total) | B20: 11521 | C20: 13362 | D20: 21645
A21: of which: Borrowings (Current) | B21: 1190 | C21: 2670 | D21: 7483
A22: of which: Gold on Loan | B22: 5090 | C22: 4938 | D22: 7043
A23: of which: Trade Payables | B23: 965 | C23: 943 | D23: 1472
A24: TOTAL EQUITY AND LIABILITIES | B24: =B16+B17+B20 -> 25088 | C24: =C16+C17+C20 -> 32862 | D24: =D16+D17+D20 -> 41075
A25: Check (Total Assets = Total Equity & Liabilities) | B25: =B11-B24 -> 0 | C25: =C11-C24 -> 0 | D25: =D11-D24 -> 0

Sheet Cash Flow
A1: Standalone Cash Flow Summary
A4: Particulars | B4: FY2023 | C4: FY2024 | D4: FY2025
A5: Net Cash from Operating Activities | B5: 1810 | C5: 2030 | D5: -170
A6: Net Cash from Investing Activities | B6: -1653 | C6: -4634 | D6: 140
A7: Net Cash from Financing Activities | B7: -155 | C7: 2757 | D7: 1
A8: Net Increase / (Decrease) in Cash | B8: =SUM(B5:B7) -> 2 | C8: =SUM(C5:C7) -> 153 | D8: =SUM(D5:D7) -> -29
A9: Cash & Cash Equivalents — Opening Balance | B9: 117 | C9: 119 | D9: 272
A10: Cash & Cash Equivalents — Closing Balance | B10: =B9+B8 -> 119 | C10: =C9+C8 -> 272 | D10: =D9+D8 -> 243

Sheet Ratio Analysis
A1: Ratio Analysis
A4: Ratio | B4: Formula | C4: FY2023 | D4: FY2024 | E4: FY2025 | F4: Interpretation
A5: Revenue Growth % | B5: (Current Yr Revenue − Prior Yr Revenue) / Prior Yr Revenue | C5: - | D5: =('Income Statement'!C5-'Income Statement'!B5)/'Income Statement'!B5 -> 0.23109485 | E5: =('Income Statement'!D5-'Income Statement'!C5)/'Income Statement'!C5 -> 0.16402768 | F5: Measures how fast sales are growing year-on-year. Titan's revenue growth slowed from 23.1% in FY24 to 16.4% in FY25 — still healthy double-digit growth, but the pace is moderating.
A6: Net Profit Growth % | B6: (Current Yr PAT − Prior Yr PAT) / Prior Yr PAT | C6: - | D6: =('Income Statement'!C18-'Income Statement'!B18)/'Income Statement'!B18 -> 0.063306331 | E6: =('Income Statement'!D18-'Income Statement'!C18)/'Income Statement'!C18 -> -0.058972912 | F6: Measures how fast bottom-line profit is growing. Unlike revenue, PAT actually declined slightly in FY25, showing profit is not keeping pace with sales growth.
A7: Gross Profit Margin % | B7: (Revenue − Cost of Materials − Purchases + Inventory Change) / Revenue | C7: =('Income Statement'!B5-'Income Statement'!B8-'Income Statement'!B9-'Income Statement'!B10)/'Income Statement'!B5 -> 0.2410243 | D7: =('Income Statement'!C5-'Income Statement'!C8-'Income Statement'!C9-'Income Statement'!C10)/'Income Statement'!C5 -> 0.21590186 | E7: =('Income Statement'!D5-'Income Statement'!D8-'Income Statement'!D9-'Income Statement'!D10)/'Income Statement'!D5 -> 0.20243609 | F7: Approximate gross margin (Revenue less material/trade cost of goods sold). Titan's gross margin has been declining (24.1% → 21.6% → 20.2%) mainly due to a higher mix of lower-margin studded/plain gold jewellery and rising gold prices.
A8: Net Profit Margin % | B8: Profit for the Year (PAT) / Revenue from Operations | C8: ='Income Statement'!B18/'Income Statement'!B5 -> 0.087091717 | D8: ='Income Statement'!C18/'Income Statement'!C5 -> 0.075221802 | E8: ='Income Statement'!D18/'Income Statement'!D5 -> 0.060811057 | F8: Shows how much of every rupee of sales becomes final profit. This has steadily declined from 8.7% to 6.1%, meaning Titan is growing sales but keeping a smaller slice as profit each year.
A9: Current Ratio | B9: Current Assets / Current Liabilities | C9: ='Balance Sheet'!B7/'Balance Sheet'!B20 -> 1.7955039 | D9: ='Balance Sheet'!C7/'Balance Sheet'!C20 -> 1.6983236 | E9: ='Balance Sheet'!D7/'Balance Sheet'!D20 -> 1.4065142 | F9: Checks whether the company can pay its short-term bills using short-term assets. A ratio above 1x is generally healthy. Titan's ratio has fallen from 1.80x to 1.41x as current liabilities (borrowings, gold on loan) grew faster than current assets.
A10: Debt to Equity Ratio | B10: Total Borrowings (Non-current + Current) / Total Equity | C10: =('Balance Sheet'!B19+'Balance Sheet'!B21)/'Balance Sheet'!B16 -> 0.099216275 | D10: =('Balance Sheet'!C19+'Balance Sheet'!C21)/'Balance Sheet'!C16 -> 0.40181227 | E10: =('Balance Sheet'!D19+'Balance Sheet'!D21)/'Balance Sheet'!D16 -> 0.47010886 | F10: Shows how much debt the company uses versus shareholders' own money. Titan's D/E has risen from 0.10x to 0.47x — still a conservative, low-debt level, but the trend shows increasing reliance on borrowings to fund growth. (Gold on loan is excluded here as it is working-capital financing, not conventional debt — see note below.)
A11: Return on Equity (ROE) % | B11: Profit for the Year (PAT) / Total Equity (year-end) | C11: ='Income Statement'!B18/'Balance Sheet'!B16 -> 0.27788894 | D11: ='Income Statement'!C18/'Balance Sheet'!C16 -> 0.24514076 | E11: ='Income Statement'!D18/'Balance Sheet'!D16 -> 0.19838201 | F11: Measures the return generated for shareholders on their invested equity. ROE has declined from 27.8% to 19.8%. Still a strong return, but equity has grown faster (through retained profits) than profit itself, diluting the return.
A12: Return on Capital Employed (ROCE) % | B12: EBIT (PBT + Finance Costs) / Capital Employed (Total Equity + Non-current Liabilities), year-end | C12: =('Income Statement'!B16+'Income Statement'!B12)/('Balance Sheet'!B16+'Balance Sheet'!B17) -> 0.34679738 | D12: =('Income Statement'!C16+'Income Statement'!C12)/('Balance Sheet'!C16+'Balance Sheet'!C17) -> 0.26087179 | E12: =('Income Statement'!D16+'Income Statement'!D12)/('Balance Sheet'!D16+'Balance Sheet'!D17) -> 0.27009779 | F12: Measures overall efficiency of using all long-term capital (equity + long-term debt) to generate operating profit. ROCE dipped in FY24 (large one-off jump in capital employed due to Ind AS 116 lease additions and long-term borrowings) then partly recovered in FY25.
A13: Asset Turnover Ratio | B13: Revenue from Operations / Total Assets (year-end) | C13: ='Income Statement'!B5/'Balance Sheet'!B11 -> 1.5254305 | D13: ='Income Statement'!C5/'Balance Sheet'!C11 -> 1.4336924 | E13: ='Income Statement'!D5/'Balance Sheet'!D11 -> 1.3351674 | F13: Shows how efficiently the company's total assets are being used to generate sales. Titan's turnover has slipped from 1.53x to 1.34x, because inventories (assets) have grown faster than revenue — largely due to gold price inflation and new store stocking.
A14: Interest Coverage Ratio | B14: EBIT (PBT + Finance Costs) / Finance Costs | C14: =('Income Statement'!B16+'Income Statement'!B12)/'Income Statement'!B12 -> 19.604167 | D14: =('Income Statement'!C16+'Income Statement'!C12)/'Income Statement'!C12 -> 10.597917 | E14: =('Income Statement'!D16+'Income Statement'!D12)/'Income Statement'!D12 -> 6.8422425 | F14: Shows how comfortably the company can pay interest on its borrowings from operating profit. Coverage has fallen from a very high 19.6x to 6.8x as both borrowings and finance costs rose sharply — still a safe level, but the cushion is thinner than before.

Sheet Trend Analysis
A1: Trend Analysis (FY2023 – FY2025)
A4: Metric | B4: FY2023 | C4: FY2024 | D4: FY2025 | E4: 3-Yr CAGR % | F4: What the Trend Indicates
A5: Revenue from Operations | B5: ='Income Statement'!B5 -> 38270 | C5: ='Income Statement'!C5 -> 47114 | D5: ='Income Statement'!D5 -> 54842 | E5: =(D5/B5)^(1/2)-1 -> 0.19709168 | F5: Revenue nearly doubled over 3 years (₹38,270 cr → ₹54,842 cr), a ~19.8% CAGR, driven by store network expansion, wedding/festive jewellery demand, and higher gold prices lifting ticket sizes.
A6: Profit for the Year (PAT) | B6: ='Income Statement'!B18 -> 3333 | C6: ='Income Statement'!C18 -> 3544 | D6: ='Income Statement'!D18 -> 3335 | E6: =(D6/B6)^(1/2)-1 -> 0.00029998501 | F6: Profit growth has NOT kept pace with revenue — it grew in FY24 but slipped in FY25. This signals margin pressure: costs (materials, employee, finance) are rising faster than sales.
A7: Total Assets | B7: ='Balance Sheet'!B11 -> 25088 | C7: ='Balance Sheet'!C11 -> 32862 | D7: ='Balance Sheet'!D11 -> 41075 | E7: =(D7/B7)^(1/2)-1 -> 0.27954559 | F7: Total assets grew ~63% over 3 years, mainly on the back of a large build-up of inventory (gold and jewellery stock) needed to support store expansion and higher gold prices.
A8: Total Liabilities (Non-current + Current) | B8: ='Balance Sheet'!B17+'Balance Sheet'!B20 -> 13094 | C8: ='Balance Sheet'!C17+'Balance Sheet'!C20 -> 18405 | D8: ='Balance Sheet'!D17+'Balance Sheet'!D20 -> 24264 | E8: =(D8/B8)^(1/2)-1 -> 0.36127237 | F8: Liabilities have grown even faster than assets in percentage terms, largely through higher short-term borrowings and gold-on-loan funding used to finance the inventory build-up.
A9: Total Equity | B9: ='Balance Sheet'!B16 -> 11994 | C9: ='Balance Sheet'!C16 -> 14457 | D9: ='Balance Sheet'!D16 -> 16811 | E9: =(D9/B9)^(1/2)-1 -> 0.18389927 | F9: Equity has grown steadily through retained profits (reserves), with no fresh equity issuance and only modest dividend payouts. A healthy sign of internal capital generation.
A10: Total Borrowings (Non-current + Current) | B10: ='Balance Sheet'!B19+'Balance Sheet'!B21 -> 1190 | C10: ='Balance Sheet'!C19+'Balance Sheet'!C21 -> 5809 | D10: ='Balance Sheet'!D19+'Balance Sheet'!D21 -> 7903 | E10: =(D10/B10)^(1/2)-1 -> 1.577048 | F10: Borrowings have risen sharply (~6.6x over 2 years) as Titan increasingly used debt to fund working capital, alongside gold on loan. Debt levels remain modest relative to equity, but the pace of increase is notable.
A11: Gold on Loan | B11: ='Balance Sheet'!B22 -> 5090 | C11: ='Balance Sheet'!C22 -> 4938 | D11: ='Balance Sheet'!D22 -> 7043 | E11: =(D11/B11)^(1/2)-1 -> 0.17630503 | F11: Gold on loan (a jewellery-sector-specific working capital tool) dipped in FY24 but rose sharply in FY25 as Titan expanded inventory to meet demand and hedge against further gold price rises.
A12: Inventories | B12: ='Balance Sheet'!B8 -> 14952 | C12: ='Balance Sheet'!C8 -> 16874 | D12: ='Balance Sheet'!D8 -> 24517 | E12: =(D12/B12)^(1/2)-1 -> 0.28051308 | F12: Inventory grew ~64% over 3 years, well ahead of revenue growth — a mix of business expansion (new stores) and gold price inflation increasing the value of stock held.
A13: Net Cash from Operating Activities | B13: ='Cash Flow'!B5 -> 1810 | C13: ='Cash Flow'!C5 -> 2030 | D13: ='Cash Flow'!D5 -> -170 | E13: n/a | F13: Operating cash flow weakened significantly and turned negative in FY25, despite strong reported profit — because a large amount of cash got tied up funding the inventory build-up (a classic 'profitable but cash-tight' pattern in growing retail businesses).
A16: Chart Data (₹ crore)
A17: Year | B17: Revenue | C17: PAT
A18: FY2023 | B18: ='Income Statement'!B5 -> 38270 | C18: ='Income Statement'!B18 -> 3333
A19: FY2024 | B19: ='Income Statement'!C5 -> 47114 | C19: ='Income Statement'!C18 -> 3544
A20: FY2025 | B20: ='Income Statement'!D5 -> 54842 | C20: ='Income Statement'!D18 -> 3335

Sheet Observations
A1: Business Observations
A4: 1. Revenue
A5: • Revenue from operations grew from ₹38,270 cr (FY23) to ₹47,114 cr (FY24) to ₹54,842 cr (FY25) — a strong ~19.8% CAGR — driven by continued store network expansion (Tanishq, Mia, CaratLane formats), robust wedding and festive jewellery demand, and a sharp rise in gold prices that increased average transaction value.
A6: • Growth momentum slowed from 23.1% in FY24 to 16.4% in FY25. This is consistent with a maturing high-growth phase and a high FY24 base, rather than a sign of demand weakness — Titan's revenue is still growing well ahead of typical retail/FMCG peers.
A8: 2. Profitability
A9: • Net profit grew modestly from ₹3,333 cr (FY23) to ₹3,544 cr (FY24), but then fell to ₹3,335 cr in FY25 — a decline despite record revenue. This is because costs grew faster than sales: cost of raw materials (mainly gold) rose from 65.5% to 80.1% of revenue over the period, squeezing gross margins from 24.1% to 20.2%.
A10: • Net profit margin has fallen steadily from 8.7% (FY23) to 7.5% (FY24) to 6.1% (FY25). Rising finance costs (₹240 cr → ₹767 cr, a 3.2x increase) from higher short-term borrowings used to fund inventory have added further pressure on the bottom line.
A11: • Profitability improved in absolute terms because of higher volumes and a growing store base, but margin compression shows the business is increasingly sensitive to gold price movements and the cost of funding its own inventory.
A13: 3. Debt Position
A14: • Total borrowings (excluding gold on loan) rose sharply from ₹1,190 cr (FY23) to ₹5,809 cr (FY24) to ₹7,903 cr (FY25). The Debt-to-Equity ratio moved from a very conservative 0.10x to 0.47x — the balance sheet is still low-risk by industry standards, but the company is clearly leaning more on borrowed funds than three years ago.
A15: • The rise in debt in FY24 included a one-time long-term borrowing of ₹3,139 cr, which was mostly repaid in FY25 (down to ₹420 cr) and replaced with more short-term borrowings (₹7,483 cr) — a shift towards funding working capital with short-term debt rather than long-term debt.
A16: • Debt position has not remained flat — it has grown meaningfully — but interest coverage (6.8x in FY25) confirms Titan can still comfortably service this debt from operating profit, even though the safety cushion is thinner than the 19.6x seen in FY23.
... A30: • Return on Equity fell from 27.8% to 19.8% over three years. This is not because the business became less profitable in absolute terms, but because equity (the denominator) has grown faster than profit (the numerator) — a natural effect of a company that retains most of its earnings.
